Workbook

Sheet Resumen Ejecutivo
A1: Análisis de mallas curriculares y aplicación de simuladores de negocios
A2: Universidad de San Buenaventura – Facultad de Ingeniería · 7 programas de pregrado · SimVenture · SimAgile · SimProject · catálogo CompanyGame · desarrollos propios
A4: 1. Alcance del análisis
A5: Se analizaron, asignatura por asignatura, las siete láminas de plan de estudios de la Facultad de Ingeniería entregadas por el cliente, para identificar dónde pueden integrarse SimVenture, SimAgile, SimProject y el catálogo CompanyGame, y dónde existe oportunidad de desarrollar simuladores propios.
A6: No se incorporó ninguna asignatura, competencia o simulador que no aparezca en esos documentos. Los criterios de calificación son los mismos usados en el análisis de la Universidad Libre, de modo que las dos universidades son comparables.
A8: 2. Espacios académicos analizados por programa
A9: Indicador | B9: Industrial | C9: Sistemas | D9: Multimedia | E9: Agroindustrial | F9: Biomédica | G9: Electrónica | H9: Biológica | I9: Total
A10: Espacios académicos | B10: =COUNTA(Industrial!C5:C62) -> 58 | C10: =COUNTA(Sistemas!C5:C68) -> 64 | D10: =COUNTA(Multimedia!C5:C62) -> 58 | E10: =COUNTA(Agroindustrial!C5:C62) -> 58 | F10: =COUNTA(Biomédica!C5:C65) -> 61 | G10: =COUNTA(Electrónica!C5:C62) -> 58 | H10: =COUNTA(Biológica!C5:C59) -> 55 | I10: =SUM(B10:H10) -> 412
A11: Créditos del programa | B11: =SUM(Industrial!D5:D62) -> 144 | C11: =SUM(Sistemas!D5:D68) -> 160 | D11: =SUM(Multimedia!D5:D62) -> 142 | E11: =SUM(Agroindustrial!D5:D62) -> 144 | F11: =SUM(Biomédica!D5:D65) -> 156 | G11: =SUM(Electrónica!D5:D62) -> 143 | H11: =SUM(Biológica!D5:D59) -> 144 | I11: =SUM(B11:H11) -> 1033
A12: Semestres | B12: 8 | C12: 9 | D12: 8 | E12: 8 | F12: 9 | G12: 8 | H12: 8
A14: 3. Grado de ajuste con el catálogo CompanyGame (número de espacios académicos)
A15: Grado de ajuste | B15: Industrial | C15: Sistemas | D15: Multimedia | E15: Agroindustrial | F15: Biomédica | G15: Electrónica | H15: Biológica | I15: Total
A16: Encaje perfecto | B16: =COUNTIF(Industrial!O5:O62,"Encaje perfecto") -> 2 | C16: =COUNTIF(Sistemas!O5:O68,"Encaje perfecto") -> 1 | D16: =COUNTIF(Multimedia!O5:O62,"Encaje perfecto") -> 0 | E16: =COUNTIF(Agroindustrial!O5:O62,"Encaje perfecto") -> 1 | F16: =COUNTIF(Biomédica!O5:O65,"Encaje perfecto") -> 0 | G16: =COUNTIF(Electrónica!O5:O62,"Encaje perfecto") -> 0 | H16: =COUNTIF(Biológica!O5:O59,"Encaje perfecto") -> 0 | I16: =SUM(B16:H16) -> 4
A17: Encaje parcial | B17: =COUNTIF(Industrial!O5:O62,"Encaje parcial") -> 2 | C17: =COUNTIF(Sistemas!O5:O68,"Encaje parcial") -> 0 | D17: =COUNTIF(Multimedia!O5:O62,"Encaje parcial") -> 0 | E17: =COUNTIF(Agroindustrial!O5:O62,"Encaje parcial") -> 0 | F17: =COUNTIF(Biomédica!O5:O65,"Encaje parcial") -> 0 | G17: =COUNTIF(Electrónica!O5:O62,"Encaje parcial") -> 2 | H17: =COUNTIF(Biológica!O5:O59,"Encaje parcial") -> 1 | I17: =SUM(B17:H17) -> 5
A18: No encaja | B18: =COUNTIF(Industrial!O5:O62,"No encaja") -> 47 | C18: =COUNTIF(Sistemas!O5:O68,"No encaja") -> 55 | D18: =COUNTIF(Multimedia!O5:O62,"No encaja") -> 55 | E18: =COUNTIF(Agroindustrial!O5:O62,"No encaja") -> 52 | F18: =COUNTIF(Biomédica!O5:O65,"No encaja") -> 54 | G18: =COUNTIF(Electrónica!O5:O62,"No encaja") -> 52 | H18: =COUNTIF(Biológica!O5:O59,"No encaja") -> 50 | I18: =SUM(B18:H18) -> 365
A19: Por definir | B19: =COUNTIF(Industrial!O5:O62,"Por definir") -> 7 | C19: =COUNTIF(Sistemas!O5:O68,"Por definir") -> 8 | D19: =COUNTIF(Multimedia!O5:O62,"Por definir") -> 3 | E19: =COUNTIF(Agroindustrial!O5:O62,"Por definir") -> 5 | F19: =COUNTIF(Biomédica!O5:O65,"Por definir") -> 7 | G19: =COUNTIF(Electrónica!O5:O62,"Por definir") -> 4 | H19: =COUNTIF(Biológica!O5:O59,"Por definir") -> 4 | I19: =SUM(B19:H19) -> 38
A21: 4. Compatibilidad Alta o Media por simulador (número de espacios académicos)
A22: Simulador | B22: Industrial | C22: Sistemas | D22: Multimedia | E22: Agroindustrial | F22: Biomédica | G22: Electrónica | H22: Biológica | I22: Total
A23: SimVenture | B23: =COUNTIF(Industrial!J5:J62,"Alta")+COUNTIF(Industrial!J5:J62,"Media") -> 0 | C23: =COUNTIF(Sistemas!J5:J68,"Alta")+COUNTIF(Sistemas!J5:J68,"Media") -> 0 | D23: =COUNTIF(Multimedia!J5:J62,"Alta")+COUNTIF(Multimedia!J5:J62,"Media") -> 0 | E23: =COUNTIF(Agroindustrial!J5:J62,"Alta")+COUNTIF(Agroindustrial!J5:J62,"Media") -> 0 | F23: =COUNTIF(Biomédica!J5:J65,"Alta")+COUNTIF(Biomédica!J5:J65,"Media") -> 0 | G23: =COUNTIF(Electrónica!J5:J62,"Alta")+COUNTIF(Electrónica!J5:J62,"Media") -> 0 | H23: =COUNTIF(Biológica!J5:J59,"Alta")+COUNTIF(Biológica!J5:J59,"Media") -> 0 | I23: =SUM(B23:H23) -> 0
A24: SimAgile | B24: =COUNTIF(Industrial!K5:K62,"Alta")+COUNTIF(Industrial!K5:K62,"Media") -> 1 | C24: =COUNTIF(Sistemas!K5:K68,"Alta")+COUNTIF(Sistemas!K5:K68,"Media") -> 1 | D24: =COUNTIF(Multimedia!K5:K62,"Alta")+COUNTIF(Multimedia!K5:K62,"Media") -> 0 | E24: =COUNTIF(Agroindustrial!K5:K62,"Alta")+COUNTIF(Agroindustrial!K5:K62,"Media") -> 0 | F24: =COUNTIF(Biomédica!K5:K65,"Alta")+COUNTIF(Biomédica!K5:K65,"Media") -> 0 | G24: =COUNTIF(Electrónica!K5:K62,"Alta")+COUNTIF(Electrónica!K5:K62,"Media") -> 1 | H24: =COUNTIF(Biológica!K5:K59,"Alta")+COUNTIF(Biológica!K5:K59,"Media") -> 0 | I24: =SUM(B24:H24) -> 3
A25: SimProject | B25: =COUNTIF(Industrial!L5:L62,"Alta")+COUNTIF(Industrial!L5:L62,"Media") -> 1 | C25: =COUNTIF(Sistemas!L5:L68,"Alta")+COUNTIF(Sistemas!L5:L68,"Media") -> 1 | D25: =COUNTIF(Multimedia!L5:L62,"Alta")+COUNTIF(Multimedia!L5:L62,"Media") -> 1 | E25: =COUNTIF(Agroindustrial!L5:L62,"Alta")+COUNTIF(Agroindustrial!L5:L62,"Media") -> 1 | F25: =COUNTIF(Biomédica!L5:L65,"Alta")+COUNTIF(Biomédica!L5:L65,"Media") -> 1 | G25: =COUNTIF(Electrónica!L5:L62,"Alta")+COUNTIF(Electrónica!L5:L62,"Media") -> 0 | H25: =COUNTIF(Biológica!L5:L59,"Alta")+COUNTIF(Biológica!L5:L59,"Media") -> 1 | I25: =SUM(B25:H25) -> 6
A26: Desarrollo propio (oportunidad) | B26: =COUNTIF(Industrial!P5:P62,"Alta")+COUNTIF(Industrial!P5:P62,"Media") -> 21 | C26: =COUNTIF(Sistemas!P5:P68,"Alta")+COUNTIF(Sistemas!P5:P68,"Media") -> 18 | D26: =COUNTIF(Multimedia!P5:P62,"Alta")+COUNTIF(Multimedia!P5:P62,"Media") -> 15 | E26: =COUNTIF(Agroindustrial!P5:P62,"Alta")+COUNTIF(Agroindustrial!P5:P62,"Media") -> 23 | F26: =COUNTIF(Biomédica!P5:P65,"Alta")+COUNTIF(Biomédica!P5:P65,"Media") -> 16 | G26: =COUNTIF(Electrónica!P5:P62,"Alta")+COUNTIF(Electrónica!P5:P62,"Media") -> 10 | H26: =COUNTIF(Biológica!P5:P59,"Alta")+COUNTIF(Biológica!P5:P59,"Media") -> 26 | I26: =SUM(B26:H26) -> 129
A27: Todos los conteos se calculan con fórmulas sobre las hojas de programa: si se ajusta una calificación, este resumen se actualiza solo.
A29: 5. Principales hallazgos
A30: • Ingeniería Industrial es, con diferencia, el programa de mayor potencial: concentra la línea de gestión empresarial (Gestión Estratégica Organizacional, Ingeniería de Costos, Ingeniería Económica, Investigación de Mercados, Gerencia de Proyectos, Diseño de Productos y Servicios) entre los semestres 4 y 7.
A31: • Ingeniería de Sistemas tiene la línea de software más larga de la facultad (semestres 2 a 9) y es el terreno natural de SimAgile y SimProject: Análisis y Diseño de Software, Diseño de Proyectos de Software, Gestión de Proyectos de Software, los dos Proyectos de Diseño y Evaluación de Proyectos de Software.
A32: • Hallazgo principal: Ingeniería de Sistemas tiene CÁTEDRA DE EMPRENDIMIENTO (semestre 7, 3 créditos), el único espacio de emprendimiento de los siete programas. Es el encaje más natural de todo el catálogo y la puerta de entrada de la familia Emprendimiento de CompanyGame.
A33: • INTRODUCCIÓN A LA INGENIERÍA está en los siete programas: un simulador CompanyGame de nivel 1-2 (T-Shirt o Sunny Day) es la entrada de mayor volumen de estudiantes de toda la facultad, con el menor costo de entrada.
A34: • PRÁCTICA PROFESIONAL también está en los siete programas, con 6 o 7 créditos. No es la venta principal, pero es un uso de baja resistencia docente que sirve para abrir la conversación en cualquier programa.
A35: • GERENCIA DE PROYECTOS DE INGENIERÍA aparece con el mismo nombre en Industrial, Agroindustrial y Biológica: una sola demostración de SimProject puede cerrar tres cursos. El catálogo CompanyGame no tiene un simulador de dirección de proyectos, así que aquí SimProject no compite con el propio portafolio.
A36: • El sello franciscano abre la puerta de ESG: FRANCISCANISMO Y ECOLOGÍA (Sistemas y Biomédica), ECOLOGÍA AGRÍCOLA y AGRICULTURA REGENERATIVA (Biológica) son espacios donde la familia ESG Management encaja como conversación de identidad institucional y no sólo de contenido.
A37: • Ingeniería Electrónica y Ingeniería Multimedia son los programas de menor encaje con el portafolio actual: Electrónica tiene una sola asignatura de gestión (Gestión de Productos Tecnológicos) y Multimedia dos (Gestión en Proyectos y Proyecto en Ingeniería). Conviene entrar por ahí y no forzar el resto de la malla.
A38: • Ingeniería Biomédica queda prácticamente fuera del portafolio actual: sólo Valoración de Proyectos e Ingeniería Clínica I y II tienen componente de gestión. Es el programa que más justifica un desarrollo propio (gestión de tecnología hospitalaria).
A39: • La línea de producción y operaciones de Industrial, Agroindustrial y Biológica (nueve asignaturas) no tiene ningún simulador aplicable, ni propio ni del catálogo. Es el mayor vacío y el desarrollo propio con más asignaturas destino de toda la facultad.
... A43: 6. Top 15 oportunidades
A44: # | B44: Programa | C44: Sem. | D44: Asignatura | F44: Grado CG | G44: Prioridad
A45: 1 | B45: Sistemas | C45: S7 | D45: Cátedra de Emprendimiento | E45: SimVenture o la familia Emprendimiento de CompanyGame | F45: Encaje perfecto | G45: Alta
A46: 2 | B46: Industrial · Agroindustrial · Biológica | C46: S5, S6 | D46: Gerencia de Proyectos de Ingeniería | E46: SimProject | F46: Encaje parcial | G46: Alta
A47: 3 | B47: Industrial | C47: S4 | D47: Gestión Estratégica Organizacional | E47: SimVenture o Business21 / Businessglobal (CompanyGame) | F47: Encaje perfecto | G47: Alta
A48: 4 | B48: Industrial · Agroindustrial | C48: S5 | D48: Ingeniería Económica | E48: SimVenture + SimProject o Kapital (CompanyGame) | F48: Encaje perfecto | G48: Alta
A49: 5 | B49: Industrial · Biológica | C49: S4 | D49: Ingeniería de Costos | E49: SimVenture o ContaTrainer (CompanyGame) | F49: Encaje perfecto | G49: Alta
A50: 6 | B50: Sistemas | C50: S9 | D50: Evaluación de Proyectos de Software | E50: SimVenture + SimProject; alternativa CompanyGame: familia Emprendimiento | F50: Encaje perfecto | G50: Alta
A51: 7 | B51: Industrial | C51: S6 | D51: Diseño de Productos y Servicios | E51: SimAgile (principal) + SimVenture o InnovaTech (CompanyGame) | F51: Encaje perfecto | G51: Alta
A52: 8 | B52: Biomédica | C52: S7 | D52: Valoración de Proyectos | E52: SimVenture + SimProject; alternativa CompanyGame: familia Emprendimiento | F52: Encaje perfecto | G52: Alta
A53: 9 | B53: Electrónica | C53: S7 | D53: Gestión de Productos Tecnológicos | E53: SimAgile (principal) + SimVenture o InnovaTech (CompanyGame) | F53: Encaje perfecto | G53: Alta
A54: 10 | B54: Sistemas | C54: S7 | D54: Gestión de Proyectos de Software | E54: SimAgile (principal) + SimProject (complementario) | F54: Encaje parcial | G54: Alta
A55: 11 | B55: Industrial | C55: S5 | D55: Investigación de Mercados | E55: SimVenture o MarketGame / SalesManager (CompanyGame) | F55: Encaje perfecto | G55: Alta
A56: 12 | B56: Agroindustrial | C56: S4 | D56: Mercadeo e Investigación de Mercados | E56: SimVenture o MarketGame / SalesManager (CompanyGame) | F56: Encaje perfecto | G56: Alta
... A59: 15 | B59: Multimedia | C59: S7 | D59: Proyecto en Ingeniería | E59: SimProject | F59: Encaje parcial | G59: Alta
A60: El detalle con el argumento comercial está en la hoja 'Priorización'.
A62: 7. Criterios de calificación
A63: ALTA | B63: El objeto central de aprendizaje de la asignatura coincide con el dominio de decisión que modela el simulador. Puede ser eje del curso o de una unidad completa.
A64: MEDIA | B64: El dominio del simulador cubre una parte de la asignatura (una unidad, un eje transversal o el contexto). Aporta como actividad complementaria o de integración.
A65: BAJA | B65: Ciencias básicas, formación humanística o dominio técnico específico sin decisiones de gestión, proyecto o negocio. El simulador no aporta a sus resultados de aprendizaje.
A66: NO EVALUABLE | B66: Espacios electivos cuyo contenido no está definido en la malla. Se tratan como espacios de inserción curricular.
A67: ENCAJE PERFECTO (CompanyGame) | B67: Un simulador del catálogo cubre el objeto central del curso.
A68: ENCAJE PARCIAL (CompanyGame) | B68: Un simulador del catálogo cubre una unidad o el contexto del curso.
A69: NO ENCAJA (CompanyGame) | B69: Ningún simulador del catálogo aplica a la asignatura.
A71: 8. Notas sobre la fuente y sus límites
A72: • Fuente única del análisis curricular: las siete láminas de plan de estudios de la Facultad de Ingeniería de la Universidad de San Buenaventura entregadas por el cliente.
A73: • Información explícita tomada de la fuente: nombre de la asignatura, semestre, número de créditos y componente de formación (leído del color del chip de créditos y contrastado contra la leyenda de cada lámina).
A74: • Información inferida por el analista: área temática, competencias, temáticas principales, relación con la gestión y todos los niveles de compatibilidad. Las láminas no incluyen contenidos programáticos ni resultados de aprendizaje; conviene validar con los microcurrículos antes de la reunión.
A75: • Fuente del catálogo CompanyGame: el cuadro de portafolio entregado por el cliente (41 simuladores en 7 familias).
A76: • La lámina de Ingeniería de Sistemas no trae leyenda de componentes de formación: esa columna queda como 'No disponible en la fuente' para los 64 espacios de ese programa.
A77: • La lámina de Ingeniería Biológica no publica componente de formación sino modalidad (presencial mediado por las TIC / virtual); siguiendo la instrucción del cliente, la columna de componente queda como no disponible.
A78: • Observaciones sobre la fuente: en tres láminas el total de créditos impreso no coincide con la suma de las tarjetas dibujadas — Sistemas semestre 5 (impreso 19, tarjetas 18), Multimedia semestre 6 (impreso 19, tarjetas 17) y Electrónica semestre 6 (impreso 18, tarjetas 17). Conviene verificarlo con la facultad.
A79: • Ingeniería Electrónica y Ingeniería Biológica comparten el mismo número de SNIES en las láminas entregadas (3828), lo que probablemente sea un error de la fuente.

Sheet Industrial
A1: Matriz de relacionamiento – Ingeniería Industrial
A2: Universidad de San Buenaventura – Facultad de Ingeniería · SNIES 4466 · 8 semestres · 58 espacios académicos · 144 créditos
A4: Programa | B4: Semestre | C4: Asignatura | D4: Créditos | E4: Componente de formación | F4: Área temática | G4: Competencias principales | H4: Temáticas principales | I4: Relación con gestión / negocio | J4: SimVenture | K4: SimAgile | L4: SimProject | M4: Simulador CompanyGame que encaja | N4: Nivel CG | O4: Grado de ajuste | P4: Desarrollo propio | Q4: Tipo de simulador que se requeriría | R4: Simulador recomendado | S4: Justificación de la recomendación | T4: Tipo de uso sugerido | U4: Prioridad comercial | V4: Origen de competencias y temáticas
A5: Ingeniería Industrial | B5: Semestre 1 | C5: Matemática Fundamental | D5: 3 | E5: Ciencias Básicas | F5: Ciencias básicas – matemáticas | G5: Razonamiento matemático y modelado cuantitativo | H5: Contenidos matemáticos propios del curso | I5: Nula | J5: Baja | K5: Baja | L5: Baja | M5: — | N5: — | O5: No encaja | P5: Baja | Q5: No requiere simulador — asignatura sin decisiones de gestión, proyecto o negocio | R5: Ninguno | S5: Asignatura de ciencias básicas sin decisiones de gestión, proyecto o negocio. | T5: No aplica | U5: Baja | V5: Inferencia académica
A6: Ingeniería Industrial | B6: Semestre 1 | C6: Química General | D6: 3 | E6: Ciencias Básicas | F6: Ciencias básicas – química | G6: Fundamentos químicos y trabajo experimental | H6: Contenidos químicos propios del curso; prácticas de laboratorio | I6: Nula para simuladores de gestión | J6: Baja | K6: Baja | L6: Baja | M6: — | N6: — | O6: No encaja | P6: Media | Q6: Laboratorio virtual de química (línea de producto distinta a los simuladores de gestión) | R6: Ninguno | S6: Sin relación con simuladores de gestión; oportunidad únicamente en laboratorio virtual. | T6: No aplica | U6: Baja | V6: Inferencia académica
A7: Ingeniería Industrial | B7: Semestre 1 | C7: Introducción a la Ingeniería | D7: 3 | E7: Ingeniería Aplicada | F7: Fundamentación profesional | G7: Comprensión del campo de acción del ingeniero; trabajo en equipo | H7: Perfil profesional, campos de la ingeniería, rol del ingeniero | I7: Media - contextualización profesional | J7: Baja | K7: Baja | L7: Baja | M7: — | N7: — | O7: No encaja | P7: Media | Q7: Cubierto parcialmente por el catálogo; el resto del curso se apoya en SimVenture, SimAgile o SimProject | R7: T-Shirt / Sunny Day (CompanyGame, nivel introductorio) | S7: Curso de contextualización sin decisiones de gestión, pero un simulador CompanyGame de nivel 1-2 funciona como primera experiencia de decisión empresarial en primer semestre. Está en los siete programas de la facultad, lo que lo convierte en la entrada de mayor volumen de estudiantes de toda la propuesta. | T7: Exploratorio | U7: Media | V7: Inferencia académica
A8: Ingeniería Industrial | B8: Semestre 1 | C8: Humanística I | D8: 2 | E8: Complementaria | F8: Formación humanística | G8: Formación humanística, ética y ciudadana | H8: Contenidos humanísticos propios del curso | I8: Baja | J8: Baja | K8: Baja | L8: Baja | M8: — | N8: — | O8: No encaja | P8: Baja | Q8: No requiere simulador — asignatura sin decisiones de gestión, proyecto o negocio | R8: Ninguno | S8: Formación humanística sin contenidos de gestión que justifiquen un simulador. | T8: No aplica | U8: Baja | V8: Inferencia académica
A9: Ingeniería Industrial | B9: Semestre 1 | C9: Humanística II | D9: 2 | E9: Complementaria | F9: Formación humanística | G9: Formación humanística, ética y ciudadana | H9: Contenidos humanísticos propios del curso | I9: Baja | J9: Baja | K9: Baja | L9: Baja | M9: — | N9: — | O9: No encaja | P9: Baja | Q9: No requiere simulador — asignatura sin decisiones de gestión, proyecto o negocio | R9: Ninguno | S9: Formación humanística sin contenidos de gestión que justifiquen un simulador. | T9: No aplica | U9: Baja | V9: Inferencia académica
A10: Ingeniería Industrial | B10: Semestre 1 | C10: Bienestar Institucional I | D10: 1 | E10: Complementaria | F10: Formación complementaria – bienestar | G10: Desarrollo personal y vida universitaria | H10: Actividades de bienestar institucional | I10: Nula | J10: Baja | K10: Baja | L10: Baja | M10: — | N10: — | O10: No encaja | P10: Baja | Q10: No requiere simulador — asignatura sin decisiones de gestión, proyecto o negocio | R10: Ninguno | S10: Espacio de bienestar institucional sin contenidos académicos de gestión. | T10: No aplica | U10: Baja | V10: Inferencia académica
A11: Ingeniería Industrial | B11: Semestre 1 | C11: Bienestar Institucional II | D11: 1 | E11: Complementaria | F11: Formación complementaria – bienestar | G11: Desarrollo personal y vida universitaria | H11: Actividades de bienestar institucional | I11: Nula | J11: Baja | K11: Baja | L11: Baja | M11: — | N11: — | O11: No encaja | P11: Baja | Q11: No requiere simulador — asignatura sin decisiones de gestión, proyecto o negocio | R11: Ninguno | S11: Espacio de bienestar institucional sin contenidos académicos de gestión. | T11: No aplica | U11: Baja | V11: Inferencia académica
A12: Ingeniería Industrial | B12: Semestre 1 | C12: Comunicación Oral y Escrita I | D12: 1 | E12: Complementaria | F12: Formación humanística | G12: Formación humanística, ética y ciudadana | H12: Contenidos humanísticos propios del curso | I12: Baja | J12: Baja | K12: Baja | L12: Baja | M12: — | N12: — | O12: No encaja | P12: Baja | Q12: No requiere simulador — asignatura sin decisiones de gestión, proyecto o negocio | R12: Ninguno | S12: Formación humanística sin contenidos de gestión que justifiquen un simulador. | T12: No aplica | U12: Baja | V12: Inferencia académica
A13: Ingeniería Industrial | B13: Semestre 1 | C13: Inglés I | D13: 2 | E13: Complementaria | F13: Formación complementaria – idioma | G13: Competencia comunicativa en inglés | H13: Comprensión y producción oral y escrita en inglés | I13: Nula | J13: Baja | K13: Baja | L13: Baja | M13: — | N13: — | O13: No encaja | P13: Baja | Q13: No requiere simulador — asignatura sin decisiones de gestión, proyecto o negocio | R13: Ninguno | S13: Curso de idioma sin contenidos de gestión. | T13: No aplica | U13: Baja | V13: Inferencia académica
A14: Ingeniería Industrial | B14: Semestre 2 | C14: Cálculo I | D14: 4 | E14: Ciencias Básicas | F14: Ciencias básicas – matemáticas | G14: Razonamiento matemático y modelado cuantitativo | H14: Contenidos matemáticos propios del curso | I14: Nula | J14: Baja | K14: Baja | L14: Baja | M14: — | N14: — | O14: No encaja | P14: Baja | Q14: No requiere simulador — asignatura sin decisiones de gestión, proyecto o negocio | R14: Ninguno | S14: Asignatura de ciencias básicas sin decisiones de gestión, proyecto o negocio. | T14: No aplica | U14: Baja | V14: Inferencia académica
A15: Ingeniería Industrial | B15: Semestre 2 | C15: Álgebra Lineal | D15: 3 | E15: Ciencias Básicas | F15: Ciencias básicas – matemáticas | G15: Razonamiento matemático y modelado cuantitativo | H15: Contenidos matemáticos propios del curso | I15: Nula | J15: Baja | K15: Baja | L15: Baja | M15: — | N15: — | O15: No encaja | P15: Baja | Q15: No requiere simulador — asignatura sin decisiones de gestión, proyecto o negocio | R15: Ninguno | S15: Asignatura de ciencias básicas sin decisiones de gestión, proyecto o negocio. | T15: No aplica | U15: Baja | V15: Inferencia académica
A16: Ingeniería Industrial | B16: Semestre 2 | C16: Física Mecánica | D16: 4 | E16: Ciencias Básicas | F16: Ciencias básicas – física | G16: Modelado físico de sistemas y experimentación | H16: Contenidos físicos propios del curso; trabajo de laboratorio | I16: Nula para simuladores de gestión | J16: Baja | K16: Baja | L16: Baja | M16: — | N16: — | O16: No encaja | P16: Media | Q16: Laboratorio virtual de física (línea de producto distinta a los simuladores de gestión) | R16: Ninguno | S16: Sin relación con simuladores de gestión. La única oportunidad es de laboratorio virtual, que es una línea de producto distinta. | T16: No aplica | U16: Baja | V16: Inferencia académica
... A62: Ingeniería Industrial | B62: Semestre 8 | C62: Inglés VIII | D62: 2 | E62: Complementaria | F62: Formación complementaria – idioma | G62: Competencia comunicativa en inglés | H62: Comprensión y producción oral y escrita en inglés | I62: Nula | J62: Baja | K62: Baja | L62: Baja | M62: — | N62: — | O62: No encaja | P62: Baja | Q62: No requiere simulador — asignatura sin decisiones de gestión, proyecto o negocio | R62: Ninguno | S62: Curso de idioma sin contenidos de gestión. | T62: No aplica | U62: Baja | V62: Inferencia académica
A64: Nota: Explícito en la lámina → programa, semestre, asignatura, créditos y componente de formación. Inferencia académica → área temática, competencias, temáticas, relación con la gestión y todos los niveles de compatibilidad. Grado de ajuste CompanyGame: Encaje perfecto = el simulador cubre el objeto central del curso; Encaje parcial = cubre una unidad o el contexto; No encaja = ningún simulador del catálogo aplica.

Sheet Sistemas
A1: Matriz de relacionamiento – Ingeniería de Sistemas
A2: Universidad de San Buenaventura – Facultad de Ingeniería · SNIES 1349 · 9 semestres · 64 espacios académicos · 160 créditos
A4: Programa | B4: Semestre | C4: Asignatura | D4: Créditos | E4: Componente de formación | F4: Área temática | G4: Competencias principales | H4: Temáticas principales | I4: Relación con gestión / negocio | J4: SimVenture | K4: SimAgile | L4: SimProject | M4: Simulador CompanyGame que encaja | N4: Nivel CG | O4: Grado de ajuste | P4: Desarrollo propio | Q4: Tipo de simulador que se requeriría | R4: Simulador recomendado | S4: Justificación de la recomendación | T4: Tipo de uso sugerido | U4: Prioridad comercial | V4: Origen de competencias y temáticas
A5: Ingeniería de Sistemas | B5: Semestre 1 | C5: Precálculo | D5: 3 | E5: No disponible en la fuente | F5: Ciencias básicas – matemáticas | G5: Razonamiento matemático y modelado cuantitativo | H5: Contenidos matemáticos propios del curso | I5: Nula | J5: Baja | K5: Baja | L5: Baja | M5: — | N5: — | O5: No encaja | P5: Baja | Q5: No requiere simulador — asignatura sin decisiones de gestión, proyecto o negocio | R5: Ninguno | S5: Asignatura de ciencias básicas sin decisiones de gestión, proyecto o negocio. | T5: No aplica | U5: Baja | V5: Inferencia académica
A6: Ingeniería de Sistemas | B6: Semestre 1 | C6: Matemáticas Discretas I | D6: 3 | E6: No disponible en la fuente | F6: Ciencias básicas – matemáticas | G6: Razonamiento matemático y modelado cuantitativo | H6: Contenidos matemáticos propios del curso | I6: Nula | J6: Baja | K6: Baja | L6: Baja | M6: — | N6: — | O6: No encaja | P6: Baja | Q6: No requiere simulador — asignatura sin decisiones de gestión, proyecto o negocio | R6: Ninguno | S6: Asignatura de ciencias básicas sin decisiones de gestión, proyecto o negocio. | T6: No aplica | U6: Baja | V6: Inferencia académica
A7: Ingeniería de Sistemas | B7: Semestre 1 | C7: Fundamentos de Programación | D7: 4 | E7: No disponible en la fuente | F7: Desarrollo de software – técnica | G7: Programación y resolución de problemas mediante código | H7: Contenidos técnicos de programación propios del curso | I7: Nula | J7: Baja | K7: Baja | L7: Baja | M7: — | N7: — | O7: No encaja | P7: Baja | Q7: No requiere simulador — asignatura sin decisiones de gestión, proyecto o negocio | R7: Ninguno | S7: Competencia técnica individual; no hay decisiones de gestión ni dinámica de equipo formalizada. Forzar un simulador aquí restaría credibilidad a la propuesta. | T7: No aplica | U7: Baja | V7: Inferencia académica
A8: Ingeniería de Sistemas | B8: Semestre 1 | C8: Introducción a la Ingeniería | D8: 3 | E8: No disponible en la fuente | F8: Fundamentación profesional | G8: Comprensión del campo de acción del ingeniero; trabajo en equipo | H8: Perfil profesional, campos de la ingeniería, rol del ingeniero | I8: Media - contextualización profesional | J8: Baja | K8: Baja | L8: Baja | M8: — | N8: — | O8: No encaja | P8: Media | Q8: Cubierto parcialmente por el catálogo; el resto del curso se apoya en SimVenture, SimAgile o SimProject | R8: T-Shirt / Sunny Day (CompanyGame, nivel introductorio) | S8: Curso de contextualización sin decisiones de gestión, pero un simulador CompanyGame de nivel 1-2 funciona como primera experiencia de decisión empresarial en primer semestre. Está en los siete programas de la facultad, lo que lo convierte en la entrada de mayor volumen de estudiantes de toda la propuesta. | T8: Exploratorio | U8: Media | V8: Inferencia académica
A9: Ingeniería de Sistemas | B9: Semestre 1 | C9: Expresión Oral y Escrita | D9: 2 | E9: No disponible en la fuente | F9: Formación humanística | G9: Formación humanística, ética y ciudadana | H9: Contenidos humanísticos propios del curso | I9: Baja | J9: Baja | K9: Baja | L9: Baja | M9: — | N9: — | O9: No encaja | P9: Baja | Q9: No requiere simulador — asignatura sin decisiones de gestión, proyecto o negocio | R9: Ninguno | S9: Formación humanística sin contenidos de gestión que justifiquen un simulador. | T9: No aplica | U9: Baja | V9: Inferencia académica
A10: Ingeniería de Sistemas | B10: Semestre 1 | C10: Identidad Institucional y Franciscana | D10: 1 | E10: No disponible en la fuente | F10: Formación institucional | G10: Desarrollo personal e identidad institucional | H10: Proyecto de vida, identidad y valores institucionales franciscanos | I10: Nula | J10: Baja | K10: Baja | L10: Baja | M10: — | N10: — | O10: No encaja | P10: Baja | Q10: No requiere simulador — asignatura sin decisiones de gestión, proyecto o negocio | R10: Ninguno | S10: Espacio de formación institucional sin contenidos de gestión. | T10: No aplica | U10: Baja | V10: Inferencia académica
A11: Ingeniería de Sistemas | B11: Semestre 1 | C11: Proyecto de Vida | D11: 2 | E11: No disponible en la fuente | F11: Formación institucional | G11: Desarrollo personal e identidad institucional | H11: Proyecto de vida, identidad y valores institucionales franciscanos | I11: Nula | J11: Baja | K11: Baja | L11: Baja | M11: — | N11: — | O11: No encaja | P11: Baja | Q11: No requiere simulador — asignatura sin decisiones de gestión, proyecto o negocio | R11: Ninguno | S11: Espacio de formación institucional sin contenidos de gestión. | T11: No aplica | U11: Baja | V11: Inferencia académica
A12: Ingeniería de Sistemas | B12: Semestre 1 | C12: Inglés I | D12: 0 | E12: No disponible en la fuente | F12: Formación complementaria – idioma | G12: Competencia comunicativa en inglés | H12: Comprensión y producción oral y escrita en inglés | I12: Nula | J12: Baja | K12: Baja | L12: Baja | M12: — | N12: — | O12: No encaja | P12: Baja | Q12: No requiere simulador — asignatura sin decisiones de gestión, proyecto o negocio | R12: Ninguno | S12: Curso de idioma sin contenidos de gestión. | T12: No aplica | U12: Baja | V12: Inferencia académica
A13: Ingeniería de Sistemas | B13: Semestre 2 | C13: Cálculo Diferencial | D13: 4 | E13: No disponible en la fuente | F13: Ciencias básicas – matemáticas | G13: Razonamiento matemático y modelado cuantitativo | H13: Contenidos matemáticos propios del curso | I13: Nula | J13: Baja | K13: Baja | L13: Baja | M13: — | N13: — | O13: No encaja | P13: Baja | Q13: No requiere simulador — asignatura sin decisiones de gestión, proyecto o negocio | R13: Ninguno | S13: Asignatura de ciencias básicas sin decisiones de gestión, proyecto o negocio. | T13: No aplica | U13: Baja | V13: Inferencia académica
A14: Ingeniería de Sistemas | B14: Semestre 2 | C14: Matemáticas Discretas II | D14: 3 | E14: No disponible en la fuente | F14: Ciencias básicas – matemáticas | G14: Razonamiento matemático y modelado cuantitativo | H14: Contenidos matemáticos propios del curso | I14: Nula | J14: Baja | K14: Baja | L14: Baja | M14: — | N14: — | O14: No encaja | P14: Baja | Q14: No requiere simulador — asignatura sin decisiones de gestión, proyecto o negocio | R14: Ninguno | S14: Asignatura de ciencias básicas sin decisiones de gestión, proyecto o negocio. | T14: No aplica | U14: Baja | V14: Inferencia académica
A15: Ingeniería de Sistemas | B15: Semestre 2 | C15: Programación Orientada a Objetos | D15: 4 | E15: No disponible en la fuente | F15: Desarrollo de software – técnica | G15: Programación y resolución de problemas mediante código | H15: Contenidos técnicos de programación propios del curso | I15: Nula | J15: Baja | K15: Baja | L15: Baja | M15: — | N15: — | O15: No encaja | P15: Baja | Q15: No requiere simulador — asignatura sin decisiones de gestión, proyecto o negocio | R15: Ninguno | S15: Competencia técnica individual; no hay decisiones de gestión ni dinámica de equipo formalizada. Forzar un simulador aquí restaría credibilidad a la propuesta. | T15: No aplica | U15: Baja | V15: Inferencia académica
A16: Ingeniería de Sistemas | B16: Semestre 2 | C16: Introducción a la Ingeniería de Software | D16: 2 | E16: No disponible en la fuente | F16: Ingeniería de software | G16: Ciclo de vida del software, requisitos, diseño y modelos de proceso | H16: Modelos de proceso (predictivos y ágiles), requisitos, diseño, modelado | I16: Alta - proceso, equipo y producto de software | J16: Baja | K16: Baja | L16: Baja | M16: — | N16: — | O16: No encaja | P16: Media | Q16: Cubierto parcialmente por el catálogo; el resto del curso se apoya en SimVenture, SimAgile o SimProject | R16: SimAgile | S16: Es donde se enseñan los marcos ágiles: SimAgile permite que el estudiante viva un ciclo completo de trabajo en equipo en lugar de memorizar roles y ceremonias. Encaje directo con una unidad completa del curso. | T16: Principal | U16: Alta | V16: Inferencia académica
... A68: Ingeniería de Sistemas | B68: Semestre 9 | C68: Ética | D68: 2 | E68: No disponible en la fuente | F68: Formación humanística – ética | G68: Razonamiento ético aplicado al ejercicio profesional | H68: Teorías éticas, ética profesional, dilemas de la práctica | I68: Baja - dilemas éticos en la decisión profesional | J68: Baja | K68: Baja | L68: Baja | M68: — | N68: — | O68: No encaja | P68: Media | Q68: DP-07: simulador de dilemas éticos en la decisión profesional | R68: ESGProject (CompanyGame) o desarrollo propio (DP-07) | S68: Los simuladores de gestión no modelan consecuencias éticas de la decisión; ESGProject cubre parcialmente la dimensión de sostenibilidad y responsabilidad. El dilema ético profesional propiamente dicho es una oportunidad de desarrollo propio transversal. | T68: Exploratorio | U68: Baja | V68: Inferencia académica
A70: Nota: Explícito en la lámina → programa, semestre, asignatura, créditos y componente de formación. Inferencia académica → área temática, competencias, temáticas, relación con la gestión y todos los niveles de compatibilidad. Grado de ajuste CompanyGame: Encaje perfecto = el simulador cubre el objeto central del curso; Encaje parcial = cubre una unidad o el contexto; No encaja = ningún simulador del catálogo aplica.

Sheet Multimedia
A1: Matriz de relacionamiento – Ingeniería Multimedia
A2: Universidad de San Buenaventura – Facultad de Ingeniería · 8 semestres · 58 espacios académicos · 142 créditos
A4: Programa | B4: Semestre | C4: Asignatura | D4: Créditos | E4: Componente de formación | F4: Área temática | G4: Competencias principales | H4: Temáticas principales | I4: Relación con gestión / negocio | J4: SimVenture | K4: SimAgile | L4: SimProject | M4: Simulador CompanyGame que encaja | N4: Nivel CG | O4: Grado de ajuste | P4: Desarrollo propio | Q4: Tipo de simulador que se requeriría | R4: Simulador recomendado | S4: Justificación de la recomendación | T4: Tipo de uso sugerido | U4: Prioridad comercial | V4: Origen de competencias y temáticas
A5: Ingeniería Multimedia | B5: Semestre 1 | C5: Precálculo | D5: 3 | E5: Ciencias Básicas | F5: Ciencias básicas – matemáticas | G5: Razonamiento matemático y modelado cuantitativo | H5: Contenidos matemáticos propios del curso | I5: Nula | J5: Baja | K5: Baja | L5: Baja | M5: — | N5: — | O5: No encaja | P5: Baja | Q5: No requiere simulador — asignatura sin decisiones de gestión, proyecto o negocio | R5: Ninguno | S5: Asignatura de ciencias básicas sin decisiones de gestión, proyecto o negocio. | T5: No aplica | U5: Baja | V5: Inferencia académica
A6: Ingeniería Multimedia | B6: Semestre 1 | C6: Matemáticas Discretas | D6: 3 | E6: Ciencias Básicas | F6: Ciencias básicas – matemáticas | G6: Razonamiento matemático y modelado cuantitativo | H6: Contenidos matemáticos propios del curso | I6: Nula | J6: Baja | K6: Baja | L6: Baja | M6: — | N6: — | O6: No encaja | P6: Baja | Q6: No requiere simulador — asignatura sin decisiones de gestión, proyecto o negocio | R6: Ninguno | S6: Asignatura de ciencias básicas sin decisiones de gestión, proyecto o negocio. | T6: No aplica | U6: Baja | V6: Inferencia académica
A7: Ingeniería Multimedia | B7: Semestre 1 | C7: Fundamentos de Programación | D7: 3 | E7: Ciencias Básicas de Ingeniería | F7: Desarrollo de software – técnica | G7: Programación y resolución de problemas mediante código | H7: Contenidos técnicos de programación propios del curso | I7: Nula | J7: Baja | K7: Baja | L7: Baja | M7: — | N7: — | O7: No encaja | P7: Baja | Q7: No requiere simulador — asignatura sin decisiones de gestión, proyecto o negocio | R7: Ninguno | S7: Competencia técnica individual; no hay decisiones de gestión ni dinámica de equipo formalizada. Forzar un simulador aquí restaría credibilidad a la propuesta. | T7: No aplica | U7: Baja | V7: Inferencia académica
A8: Ingeniería Multimedia | B8: Semestre 1 | C8: Introducción a la Ingeniería | D8: 3 | E8: Ciencias Básicas de Ingeniería | F8: Fundamentación profesional | G8: Comprensión del campo de acción del ingeniero; trabajo en equipo | H8: Perfil profesional, campos de la ingeniería, rol del ingeniero | I8: Media - contextualización profesional | J8: Baja | K8: Baja | L8: Baja | M8: — | N8: — | O8: No encaja | P8: Media | Q8: Cubierto parcialmente por el catálogo; el resto del curso se apoya en SimVenture, SimAgile o SimProject | R8: T-Shirt / Sunny Day (CompanyGame, nivel introductorio) | S8: Curso de contextualización sin decisiones de gestión, pero un simulador CompanyGame de nivel 1-2 funciona como primera experiencia de decisión empresarial en primer semestre. Está en los siete programas de la facultad, lo que lo convierte en la entrada de mayor volumen de estudiantes de toda la propuesta. | T8: Exploratorio | U8: Media | V8: Inferencia académica
A9: Ingeniería Multimedia | B9: Semestre 1 | C9: Comunicación Oral y Escrita I | D9: 1 | E9: Complementaria | F9: Formación humanística | G9: Formación humanística, ética y ciudadana | H9: Contenidos humanísticos propios del curso | I9: Baja | J9: Baja | K9: Baja | L9: Baja | M9: — | N9: — | O9: No encaja | P9: Baja | Q9: No requiere simulador — asignatura sin decisiones de gestión, proyecto o negocio | R9: Ninguno | S9: Formación humanística sin contenidos de gestión que justifiquen un simulador. | T9: No aplica | U9: Baja | V9: Inferencia académica
A10: Ingeniería Multimedia | B10: Semestre 1 | C10: Humanística I | D10: 2 | E10: Complementaria | F10: Formación humanística | G10: Formación humanística, ética y ciudadana | H10: Contenidos humanísticos propios del curso | I10: Baja | J10: Baja | K10: Baja | L10: Baja | M10: — | N10: — | O10: No encaja | P10: Baja | Q10: No requiere simulador — asignatura sin decisiones de gestión, proyecto o negocio | R10: Ninguno | S10: Formación humanística sin contenidos de gestión que justifiquen un simulador. | T10: No aplica | U10: Baja | V10: Inferencia académica
A11: Ingeniería Multimedia | B11: Semestre 1 | C11: Humanística II | D11: 2 | E11: Complementaria | F11: Formación humanística | G11: Formación humanística, ética y ciudadana | H11: Contenidos humanísticos propios del curso | I11: Baja | J11: Baja | K11: Baja | L11: Baja | M11: — | N11: — | O11: No encaja | P11: Baja | Q11: No requiere simulador — asignatura sin decisiones de gestión, proyecto o negocio | R11: Ninguno | S11: Formación humanística sin contenidos de gestión que justifiquen un simulador. | T11: No aplica | U11: Baja | V11: Inferencia académica
A12: Ingeniería Multimedia | B12: Semestre 1 | C12: Inglés I | D12: 2 | E12: Complementaria | F12: Formación complementaria – idioma | G12: Competencia comunicativa en inglés | H12: Comprensión y producción oral y escrita en inglés | I12: Nula | J12: Baja | K12: Baja | L12: Baja | M12: — | N12: — | O12: No encaja | P12: Baja | Q12: No requiere simulador — asignatura sin decisiones de gestión, proyecto o negocio | R12: Ninguno | S12: Curso de idioma sin contenidos de gestión. | T12: No aplica | U12: Baja | V12: Inferencia académica
A13: Ingeniería Multimedia | B13: Semestre 2 | C13: Física Mecánica | D13: 4 | E13: Ciencias Básicas | F13: Ciencias básicas – física | G13: Modelado físico de sistemas y experimentación | H13: Contenidos físicos propios del curso; trabajo de laboratorio | I13: Nula para simuladores de gestión | J13: Baja | K13: Baja | L13: Baja | M13: — | N13: — | O13: No encaja | P13: Media | Q13: Laboratorio virtual de física (línea de producto distinta a los simuladores de gestión) | R13: Ninguno | S13: Sin relación con simuladores de gestión. La única oportunidad es de laboratorio virtual, que es una línea de producto distinta. | T13: No aplica | U13: Baja | V13: Inferencia académica
A14: Ingeniería Multimedia | B14: Semestre 2 | C14: Cálculo I | D14: 4 | E14: Ciencias Básicas | F14: Ciencias básicas – matemáticas | G14: Razonamiento matemático y modelado cuantitativo | H14: Contenidos matemáticos propios del curso | I14: Nula | J14: Baja | K14: Baja | L14: Baja | M14: — | N14: — | O14: No encaja | P14: Baja | Q14: No requiere simulador — asignatura sin decisiones de gestión, proyecto o negocio | R14: Ninguno | S14: Asignatura de ciencias básicas sin decisiones de gestión, proyecto o negocio. | T14: No aplica | U14: Baja | V14: Inferencia académica
A15: Ingeniería Multimedia | B15: Semestre 2 | C15: Programación Orientada a Objetos | D15: 3 | E15: Ciencias Básicas de Ingeniería | F15: Desarrollo de software – técnica | G15: Programación y resolución de problemas mediante código | H15: Contenidos técnicos de programación propios del curso | I15: Nula | J15: Baja | K15: Baja | L15: Baja | M15: — | N15: — | O15: No encaja | P15: Baja | Q15: No requiere simulador — asignatura sin decisiones de gestión, proyecto o negocio | R15: Ninguno | S15: Competencia técnica individual; no hay decisiones de gestión ni dinámica de equipo formalizada. Forzar un simulador aquí restaría credibilidad a la propuesta. | T15: No aplica | U15: Baja | V15: Inferencia académica
A16: Ingeniería Multimedia | B16: Semestre 2 | C16: Taller Multimedia | D16: 2 | E16: Ingeniería Aplicada | F16: Producción de medios digitales | G16: Producción y postproducción de contenidos digitales | H16: Contenidos técnicos y creativos propios del curso | I16: Baja | J16: Baja | K16: Baja | L16: Baja | M16: — | N16: — | O16: No encaja | P16: Media | Q16: DP-11: simulador de gestión de una producción audiovisual (presupuesto, cronograma y equipo creativo) | R16: Ninguno | S16: Producción creativa sin decisiones de gestión modeladas por el portafolio. Un simulador propio de gestión de producción audiovisual sería la única vía. | T16: No aplica | U16: Baja | V16: Inferencia académica
... A62: Ingeniería Multimedia | B62: Semestre 8 | C62: Inglés VIII | D62: 2 | E62: Complementaria | F62: Formación complementaria – idioma | G62: Competencia comunicativa en inglés | H62: Comprensión y producción oral y escrita en inglés | I62: Nula | J62: Baja | K62: Baja | L62: Baja | M62: — | N62: — | O62: No encaja | P62: Baja | Q62: No requiere simulador — asignatura sin decisiones de gestión, proyecto o negocio | R62: Ninguno | S62: Curso de idioma sin contenidos de gestión. | T62: No aplica | U62: Baja | V62: Inferencia académica
A64: Nota: Explícito en la lámina → programa, semestre, asignatura, créditos y componente de formación. Inferencia académica → área temática, competencias, temáticas, relación con la gestión y todos los niveles de compatibilidad. Grado de ajuste CompanyGame: Encaje perfecto = el simulador cubre el objeto central del curso; Encaje parcial = cubre una unidad o el contexto; No encaja = ningún simulador del catálogo aplica.

Sheet Agroindustrial
A1: Matriz de relacionamiento – Ingeniería Agroindustrial
A2: Universidad de San Buenaventura – Facultad de Ingeniería · 8 semestres · 58 espacios académicos · 144 créditos
A4: Programa | B4: Semestre | C4: Asignatura | D4: Créditos | E4: Componente de formación | F4: Área temática | G4: Competencias principales | H4: Temáticas principales | I4: Relación con gestión / negocio | J4: SimVenture | K4: SimAgile | L4: SimProject | M4: Simulador CompanyGame que encaja | N4: Nivel CG | O4: Grado de ajuste | P4: Desarrollo propio | Q4: Tipo de simulador que se requeriría | R4: Simulador recomendado | S4: Justificación de la recomendación | T4: Tipo de uso sugerido | U4: Prioridad comercial | V4: Origen de competencias y temáticas
A5: Ingeniería Agroindustrial | B5: Semestre 1 | C5: Matemáticas Fundamentales | D5: 3 | E5: Ciencias Básicas | F5: Ciencias básicas – matemáticas | G5: Razonamiento matemático y modelado cuantitativo | H5: Contenidos matemáticos propios del curso | I5: Nula | J5: Baja | K5: Baja | L5: Baja | M5: — | N5: — | O5: No encaja | P5: Baja | Q5: No requiere simulador — asignatura sin decisiones de gestión, proyecto o negocio | R5: Ninguno | S5: Asignatura de ciencias básicas sin decisiones de gestión, proyecto o negocio. | T5: No aplica | U5: Baja | V5: Inferencia académica
A6: Ingeniería Agroindustrial | B6: Semestre 1 | C6: Química | D6: 3 | E6: Ciencias Básicas | F6: Ciencias básicas – química | G6: Fundamentos químicos y trabajo experimental | H6: Contenidos químicos propios del curso; prácticas de laboratorio | I6: Nula para simuladores de gestión | J6: Baja | K6: Baja | L6: Baja | M6: — | N6: — | O6: No encaja | P6: Media | Q6: Laboratorio virtual de química (línea de producto distinta a los simuladores de gestión) | R6: Ninguno | S6: Sin relación con simuladores de gestión; oportunidad únicamente en laboratorio virtual. | T6: No aplica | U6: Baja | V6: Inferencia académica
A7: Ingeniería Agroindustrial | B7: Semestre 1 | C7: Introducción a la Ingeniería | D7: 3 | E7: Ciencias Básicas de Ingeniería | F7: Fundamentación profesional | G7: Comprensión del campo de acción del ingeniero; trabajo en equipo | H7: Perfil profesional, campos de la ingeniería, rol del ingeniero | I7: Media - contextualización profesional | J7: Baja | K7: Baja | L7: Baja | M7: — | N7: — | O7: No encaja | P7: Media | Q7: Cubierto parcialmente por el catálogo; el resto del curso se apoya en SimVenture, SimAgile o SimProject | R7: T-Shirt / Sunny Day (CompanyGame, nivel introductorio) | S7: Curso de contextualización sin decisiones de gestión, pero un simulador CompanyGame de nivel 1-2 funciona como primera experiencia de decisión empresarial en primer semestre. Está en los siete programas de la facultad, lo que lo convierte en la entrada de mayor volumen de estudiantes de toda la propuesta. | T7: Exploratorio | U7: Media | V7: Inferencia académica
A8: Ingeniería Agroindustrial | B8: Semestre 1 | C8: Humanística I | D8: 2 | E8: Complementaria | F8: Formación humanística | G8: Formación humanística, ética y ciudadana | H8: Contenidos humanísticos propios del curso | I8: Baja | J8: Baja | K8: Baja | L8: Baja | M8: — | N8: — | O8: No encaja | P8: Baja | Q8: No requiere simulador — asignatura sin decisiones de gestión, proyecto o negocio | R8: Ninguno | S8: Formación humanística sin contenidos de gestión que justifiquen un simulador. | T8: No aplica | U8: Baja | V8: Inferencia académica
A9: Ingeniería Agroindustrial | B9: Semestre 1 | C9: Humanística II | D9: 2 | E9: Complementaria | F9: Formación humanística | G9: Formación humanística, ética y ciudadana | H9: Contenidos humanísticos propios del curso | I9: Baja | J9: Baja | K9: Baja | L9: Baja | M9: — | N9: — | O9: No encaja | P9: Baja | Q9: No requiere simulador — asignatura sin decisiones de gestión, proyecto o negocio | R9: Ninguno | S9: Formación humanística sin contenidos de gestión que justifiquen un simulador. | T9: No aplica | U9: Baja | V9: Inferencia académica
A10: Ingeniería Agroindustrial | B10: Semestre 1 | C10: Curso Formativo de Bienestar Institucional I | D10: 1 | E10: Complementaria | F10: Formación complementaria – bienestar | G10: Desarrollo personal y vida universitaria | H10: Actividades de bienestar institucional | I10: Nula | J10: Baja | K10: Baja | L10: Baja | M10: — | N10: — | O10: No encaja | P10: Baja | Q10: No requiere simulador — asignatura sin decisiones de gestión, proyecto o negocio | R10: Ninguno | S10: Espacio de bienestar institucional sin contenidos académicos de gestión. | T10: No aplica | U10: Baja | V10: Inferencia académica
A11: Ingeniería Agroindustrial | B11: Semestre 1 | C11: Curso Formativo de Bienestar Institucional II | D11: 1 | E11: Complementaria | F11: Formación complementaria – bienestar | G11: Desarrollo personal y vida universitaria | H11: Actividades de bienestar institucional | I11: Nula | J11: Baja | K11: Baja | L11: Baja | M11: — | N11: — | O11: No encaja | P11: Baja | Q11: No requiere simulador — asignatura sin decisiones de gestión, proyecto o negocio | R11: Ninguno | S11: Espacio de bienestar institucional sin contenidos académicos de gestión. | T11: No aplica | U11: Baja | V11: Inferencia académica
A12: Ingeniería Agroindustrial | B12: Semestre 1 | C12: Comunicación Oral y Escrita I | D12: 1 | E12: Complementaria | F12: Formación humanística | G12: Formación humanística, ética y ciudadana | H12: Contenidos humanísticos propios del curso | I12: Baja | J12: Baja | K12: Baja | L12: Baja | M12: — | N12: — | O12: No encaja | P12: Baja | Q12: No requiere simulador — asignatura sin decisiones de gestión, proyecto o negocio | R12: Ninguno | S12: Formación humanística sin contenidos de gestión que justifiquen un simulador. | T12: No aplica | U12: Baja | V12: Inferencia académica
A13: Ingeniería Agroindustrial | B13: Semestre 1 | C13: Inglés I | D13: 2 | E13: Complementaria | F13: Formación complementaria – idioma | G13: Competencia comunicativa en inglés | H13: Comprensión y producción oral y escrita en inglés | I13: Nula | J13: Baja | K13: Baja | L13: Baja | M13: — | N13: — | O13: No encaja | P13: Baja | Q13: No requiere simulador — asignatura sin decisiones de gestión, proyecto o negocio | R13: Ninguno | S13: Curso de idioma sin contenidos de gestión. | T13: No aplica | U13: Baja | V13: Inferencia académica
A14: Ingeniería Agroindustrial | B14: Semestre 2 | C14: Física Mecánica | D14: 4 | E14: Ciencias Básicas | F14: Ciencias básicas – física | G14: Modelado físico de sistemas y experimentación | H14: Contenidos físicos propios del curso; trabajo de laboratorio | I14: Nula para simuladores de gestión | J14: Baja | K14: Baja | L14: Baja | M14: — | N14: — | O14: No encaja | P14: Media | Q14: Laboratorio virtual de física (línea de producto distinta a los simuladores de gestión) | R14: Ninguno | S14: Sin relación con simuladores de gestión. La única oportunidad es de laboratorio virtual, que es una línea de producto distinta. | T14: No aplica | U14: Baja | V14: Inferencia académica
A15: Ingeniería Agroindustrial | B15: Semestre 2 | C15: Cálculo I | D15: 4 | E15: Ciencias Básicas | F15: Ciencias básicas – matemáticas | G15: Razonamiento matemático y modelado cuantitativo | H15: Contenidos matemáticos propios del curso | I15: Nula | J15: Baja | K15: Baja | L15: Baja | M15: — | N15: — | O15: No encaja | P15: Baja | Q15: No requiere simulador — asignatura sin decisiones de gestión, proyecto o negocio | R15: Ninguno | S15: Asignatura de ciencias básicas sin decisiones de gestión, proyecto o negocio. | T15: No aplica | U15: Baja | V15: Inferencia académica
A16: Ingeniería Agroindustrial | B16: Semestre 2 | C16: Bioquímica | D16: 3 | E16: Ciencias Básicas | F16: Ciencias básicas – química | G16: Fundamentos químicos y trabajo experimental | H16: Contenidos químicos propios del curso; prácticas de laboratorio | I16: Nula para simuladores de gestión | J16: Baja | K16: Baja | L16: Baja | M16: — | N16: — | O16: No encaja | P16: Media | Q16: Laboratorio virtual de química (línea de producto distinta a los simuladores de gestión) | R16: Ninguno | S16: Sin relación con simuladores de gestión; oportunidad únicamente en laboratorio virtual. | T16: No aplica | U16: Baja | V16: Inferencia académica
... A62: Ingeniería Agroindustrial | B62: Semestre 8 | C62: Inglés VIII | D62: 2 | E62: Complementaria | F62: Formación complementaria – idioma | G62: Competencia comunicativa en inglés | H62: Comprensión y producción oral y escrita en inglés | I62: Nula | J62: Baja | K62: Baja | L62: Baja | M62: — | N62: — | O62: No encaja | P62: Baja | Q62: No requiere simulador — asignatura sin decisiones de gestión, proyecto o negocio | R62: Ninguno | S62: Curso de idioma sin contenidos de gestión. | T62: No aplica | U62: Baja | V62: Inferencia académica
A64: Nota: Explícito en la lámina → programa, semestre, asignatura, créditos y componente de formación. Inferencia académica → área temática, competencias, temáticas, relación con la gestión y todos los niveles de compatibilidad. Grado de ajuste CompanyGame: Encaje perfecto = el simulador cubre el objeto central del curso; Encaje parcial = cubre una unidad o el contexto; No encaja = ningún simulador del catálogo aplica.

Sheet Biomédica
A1: Matriz de relacionamiento – Ingeniería Biomédica
A2: Universidad de San Buenaventura – Facultad de Ingeniería · 9 semestres · 61 espacios académicos · 156 créditos
A4: Programa | B4: Semestre | C4: Asignatura | D4: Créditos | E4: Componente de formación | F4: Área temática | G4: Competencias principales | H4: Temáticas principales | I4: Relación con gestión / negocio | J4: SimVenture | K4: SimAgile | L4: SimProject | M4: Simulador CompanyGame que encaja | N4: Nivel CG | O4: Grado de ajuste | P4: Desarrollo propio | Q4: Tipo de simulador que se requeriría | R4: Simulador recomendado | S4: Justificación de la recomendación | T4: Tipo de uso sugerido | U4: Prioridad comercial | V4: Origen de competencias y temáticas
A5: Ingeniería Biomédica | B5: Semestre 1 | C5: Biología Celular | D5: 3 | E5: Ciencias Básicas | F5: Ciencias básicas – biología y bioprocesos | G5: Fundamentos biológicos aplicados a la ingeniería | H5: Contenidos biológicos y de bioprocesos propios del curso | I5: Nula para simuladores de gestión | J5: Baja | K5: Baja | L5: Baja | M5: — | N5: — | O5: No encaja | P5: Media | Q5: Laboratorio o simulador virtual de bioprocesos (línea de producto distinta) | R5: Ninguno | S5: Contenido científico-técnico sin decisiones de gestión. La oportunidad sería un laboratorio o simulador de bioprocesos, línea distinta a los simuladores de negocio. | T5: No aplica | U5: Baja | V5: Inferencia académica
A6: Ingeniería Biomédica | B6: Semestre 1 | C6: Precálculo | D6: 3 | E6: Ciencias Básicas | F6: Ciencias básicas – matemáticas | G6: Razonamiento matemático y modelado cuantitativo | H6: Contenidos matemáticos propios del curso | I6: Nula | J6: Baja | K6: Baja | L6: Baja | M6: — | N6: — | O6: No encaja | P6: Baja | Q6: No requiere simulador — asignatura sin decisiones de gestión, proyecto o negocio | R6: Ninguno | S6: Asignatura de ciencias básicas sin decisiones de gestión, proyecto o negocio. | T6: No aplica | U6: Baja | V6: Inferencia académica
A7: Ingeniería Biomédica | B7: Semestre 1 | C7: Dibujo para Ingeniería | D7: 2 | E7: Ciencias Básicas de Ingeniería | F7: Electrónica, hardware e infraestructura | G7: Diseño y operación de sistemas electrónicos y de infraestructura | H7: Contenidos técnicos propios del curso | I7: Nula | J7: Baja | K7: Baja | L7: Baja | M7: — | N7: — | O7: No encaja | P7: Baja | Q7: No requiere simulador — asignatura sin decisiones de gestión, proyecto o negocio | R7: Ninguno | S7: Dominio técnico sin decisiones de gestión, proyecto o negocio. | T7: No aplica | U7: Baja | V7: Inferencia académica
A8: Ingeniería Biomédica | B8: Semestre 1 | C8: Introducción a la Ingeniería | D8: 3 | E8: Ciencias Básicas de Ingeniería | F8: Fundamentación profesional | G8: Comprensión del campo de acción del ingeniero; trabajo en equipo | H8: Perfil profesional, campos de la ingeniería, rol del ingeniero | I8: Media - contextualización profesional | J8: Baja | K8: Baja | L8: Baja | M8: — | N8: — | O8: No encaja | P8: Media | Q8: Cubierto parcialmente por el catálogo; el resto del curso se apoya en SimVenture, SimAgile o SimProject | R8: T-Shirt / Sunny Day (CompanyGame, nivel introductorio) | S8: Curso de contextualización sin decisiones de gestión, pero un simulador CompanyGame de nivel 1-2 funciona como primera experiencia de decisión empresarial en primer semestre. Está en los siete programas de la facultad, lo que lo convierte en la entrada de mayor volumen de estudiantes de toda la propuesta. | T8: Exploratorio | U8: Media | V8: Inferencia académica
A9: Ingeniería Biomédica | B9: Semestre 1 | C9: Expresión Oral y Escrita | D9: 1 | E9: Complementaria | F9: Formación humanística | G9: Formación humanística, ética y ciudadana | H9: Contenidos humanísticos propios del curso | I9: Baja | J9: Baja | K9: Baja | L9: Baja | M9: — | N9: — | O9: No encaja | P9: Baja | Q9: No requiere simulador — asignatura sin decisiones de gestión, proyecto o negocio | R9: Ninguno | S9: Formación humanística sin contenidos de gestión que justifiquen un simulador. | T9: No aplica | U9: Baja | V9: Inferencia académica
A10: Ingeniería Biomédica | B10: Semestre 1 | C10: Identidad Institucional y Franciscana | D10: 1 | E10: Complementaria | F10: Formación institucional | G10: Desarrollo personal e identidad institucional | H10: Proyecto de vida, identidad y valores institucionales franciscanos | I10: Nula | J10: Baja | K10: Baja | L10: Baja | M10: — | N10: — | O10: No encaja | P10: Baja | Q10: No requiere simulador — asignatura sin decisiones de gestión, proyecto o negocio | R10: Ninguno | S10: Espacio de formación institucional sin contenidos de gestión. | T10: No aplica | U10: Baja | V10: Inferencia académica
A11: Ingeniería Biomédica | B11: Semestre 1 | C11: Proyecto de Vida | D11: 2 | E11: Complementaria | F11: Formación institucional | G11: Desarrollo personal e identidad institucional | H11: Proyecto de vida, identidad y valores institucionales franciscanos | I11: Nula | J11: Baja | K11: Baja | L11: Baja | M11: — | N11: — | O11: No encaja | P11: Baja | Q11: No requiere simulador — asignatura sin decisiones de gestión, proyecto o negocio | R11: Ninguno | S11: Espacio de formación institucional sin contenidos de gestión. | T11: No aplica | U11: Baja | V11: Inferencia académica
A12: Ingeniería Biomédica | B12: Semestre 1 | C12: Bienestar Institucional I | D12: 1 | E12: Complementaria | F12: Formación complementaria – bienestar | G12: Desarrollo personal y vida universitaria | H12: Actividades de bienestar institucional | I12: Nula | J12: Baja | K12: Baja | L12: Baja | M12: — | N12: — | O12: No encaja | P12: Baja | Q12: No requiere simulador — asignatura sin decisiones de gestión, proyecto o negocio | R12: Ninguno | S12: Espacio de bienestar institucional sin contenidos académicos de gestión. | T12: No aplica | U12: Baja | V12: Inferencia académica
A13: Ingeniería Biomédica | B13: Semestre 1 | C13: Inglés I | D13: 1 | E13: Complementaria | F13: Formación complementaria – idioma | G13: Competencia comunicativa en inglés | H13: Comprensión y producción oral y escrita en inglés | I13: Nula | J13: Baja | K13: Baja | L13: Baja | M13: — | N13: — | O13: No encaja | P13: Baja | Q13: No requiere simulador — asignatura sin decisiones de gestión, proyecto o negocio | R13: Ninguno | S13: Curso de idioma sin contenidos de gestión. | T13: No aplica | U13: Baja | V13: Inferencia académica
A14: Ingeniería Biomédica | B14: Semestre 2 | C14: Física Mecánica | D14: 4 | E14: Ciencias Básicas | F14: Ciencias básicas – física | G14: Modelado físico de sistemas y experimentación | H14: Contenidos físicos propios del curso; trabajo de laboratorio | I14: Nula para simuladores de gestión | J14: Baja | K14: Baja | L14: Baja | M14: — | N14: — | O14: No encaja | P14: Media | Q14: Laboratorio virtual de física (línea de producto distinta a los simuladores de gestión) | R14: Ninguno | S14: Sin relación con simuladores de gestión. La única oportunidad es de laboratorio virtual, que es una línea de producto distinta. | T14: No aplica | U14: Baja | V14: Inferencia académica
A15: Ingeniería Biomédica | B15: Semestre 2 | C15: Química | D15: 4 | E15: Ciencias Básicas | F15: Ciencias básicas – química | G15: Fundamentos químicos y trabajo experimental | H15: Contenidos químicos propios del curso; prácticas de laboratorio | I15: Nula para simuladores de gestión | J15: Baja | K15: Baja | L15: Baja | M15: — | N15: — | O15: No encaja | P15: Media | Q15: Laboratorio virtual de química (línea de producto distinta a los simuladores de gestión) | R15: Ninguno | S15: Sin relación con simuladores de gestión; oportunidad únicamente en laboratorio virtual. | T15: No aplica | U15: Baja | V15: Inferencia académica
A16: Ingeniería Biomédica | B16: Semestre 2 | C16: Cálculo Diferencial | D16: 4 | E16: Ciencias Básicas | F16: Ciencias básicas – matemáticas | G16: Razonamiento matemático y modelado cuantitativo | H16: Contenidos matemáticos propios del curso | I16: Nula | J16: Baja | K16: Baja | L16: Baja | M16: — | N16: — | O16: No encaja | P16: Baja | Q16: No requiere simulador — asignatura sin decisiones de gestión, proyecto o negocio | R16: Ninguno | S16: Asignatura de ciencias básicas sin decisiones de gestión, proyecto o negocio. | T16: No aplica | U16: Baja | V16: Inferencia académica
... A65: Ingeniería Biomédica | B65: Semestre 9 | C65: Inglés VIII | D65: 1 | E65: Complementaria | F65: Formación complementaria – idioma | G65: Competencia comunicativa en inglés | H65: Comprensión y producción oral y escrita en inglés | I65: Nula | J65: Baja | K65: Baja | L65: Baja | M65: — | N65: — | O65: No encaja | P65: Baja | Q65: No requiere simulador — asignatura sin decisiones de gestión, proyecto o negocio | R65: Ninguno | S65: Curso de idioma sin contenidos de gestión. | T65: No aplica | U65: Baja | V65: Inferencia académica
A67: Nota: Explícito en la lámina → programa, semestre, asignatura, créditos y componente de formación. Inferencia académica → área temática, competencias, temáticas, relación con la gestión y todos los niveles de compatibilidad. Grado de ajuste CompanyGame: Encaje perfecto = el simulador cubre el objeto central del curso; Encaje parcial = cubre una unidad o el contexto; No encaja = ningún simulador del catálogo aplica.

Sheet Electrónica
A1: Matriz de relacionamiento – Ingeniería Electrónica
A2: Universidad de San Buenaventura – Facultad de Ingeniería · SNIES 3828 · 8 semestres · 58 espacios académicos · 143 créditos
A4: Programa | B4: Semestre | C4: Asignatura | D4: Créditos | E4: Componente de formación | F4: Área temática | G4: Competencias principales | H4: Temáticas principales | I4: Relación con gestión / negocio | J4: SimVenture | K4: SimAgile | L4: SimProject | M4: Simulador CompanyGame que encaja | N4: Nivel CG | O4: Grado de ajuste | P4: Desarrollo propio | Q4: Tipo de simulador que se requeriría | R4: Simulador recomendado | S4: Justificación de la recomendación | T4: Tipo de uso sugerido | U4: Prioridad comercial | V4: Origen de competencias y temáticas
A5: Ingeniería Electrónica | B5: Semestre 1 | C5: Introducción a la Ingeniería | D5: 3 | E5: Ciencias Básicas de Ingeniería | F5: Fundamentación profesional | G5: Comprensión del campo de acción del ingeniero; trabajo en equipo | H5: Perfil profesional, campos de la ingeniería, rol del ingeniero | I5: Media - contextualización profesional | J5: Baja | K5: Baja | L5: Baja | M5: — | N5: — | O5: No encaja | P5: Media | Q5: Cubierto parcialmente por el catálogo; el resto del curso se apoya en SimVenture, SimAgile o SimProject | R5: T-Shirt / Sunny Day (CompanyGame, nivel introductorio) | S5: Curso de contextualización sin decisiones de gestión, pero un simulador CompanyGame de nivel 1-2 funciona como primera experiencia de decisión empresarial en primer semestre. Está en los siete programas de la facultad, lo que lo convierte en la entrada de mayor volumen de estudiantes de toda la propuesta. | T5: Exploratorio | U5: Media | V5: Inferencia académica
A6: Ingeniería Electrónica | B6: Semestre 1 | C6: Comunicación Oral y Escrita I | D6: 1 | E6: Ciencias Básicas de Ingeniería | F6: Formación humanística | G6: Formación humanística, ética y ciudadana | H6: Contenidos humanísticos propios del curso | I6: Baja | J6: Baja | K6: Baja | L6: Baja | M6: — | N6: — | O6: No encaja | P6: Baja | Q6: No requiere simulador — asignatura sin decisiones de gestión, proyecto o negocio | R6: Ninguno | S6: Formación humanística sin contenidos de gestión que justifiquen un simulador. | T6: No aplica | U6: Baja | V6: Inferencia académica
A7: Ingeniería Electrónica | B7: Semestre 1 | C7: Humanística I | D7: 2 | E7: Complementaria | F7: Formación humanística | G7: Formación humanística, ética y ciudadana | H7: Contenidos humanísticos propios del curso | I7: Baja | J7: Baja | K7: Baja | L7: Baja | M7: — | N7: — | O7: No encaja | P7: Baja | Q7: No requiere simulador — asignatura sin decisiones de gestión, proyecto o negocio | R7: Ninguno | S7: Formación humanística sin contenidos de gestión que justifiquen un simulador. | T7: No aplica | U7: Baja | V7: Inferencia académica
A8: Ingeniería Electrónica | B8: Semestre 1 | C8: Humanística II | D8: 2 | E8: Complementaria | F8: Formación humanística | G8: Formación humanística, ética y ciudadana | H8: Contenidos humanísticos propios del curso | I8: Baja | J8: Baja | K8: Baja | L8: Baja | M8: — | N8: — | O8: No encaja | P8: Baja | Q8: No requiere simulador — asignatura sin decisiones de gestión, proyecto o negocio | R8: Ninguno | S8: Formación humanística sin contenidos de gestión que justifiquen un simulador. | T8: No aplica | U8: Baja | V8: Inferencia académica
A9: Ingeniería Electrónica | B9: Semestre 1 | C9: Matemáticas Fundamentales | D9: 3 | E9: Complementaria | F9: Ciencias básicas – matemáticas | G9: Razonamiento matemático y modelado cuantitativo | H9: Contenidos matemáticos propios del curso | I9: Nula | J9: Baja | K9: Baja | L9: Baja | M9: — | N9: — | O9: No encaja | P9: Baja | Q9: No requiere simulador — asignatura sin decisiones de gestión, proyecto o negocio | R9: Ninguno | S9: Asignatura de ciencias básicas sin decisiones de gestión, proyecto o negocio. | T9: No aplica | U9: Baja | V9: Inferencia académica
A10: Ingeniería Electrónica | B10: Semestre 1 | C10: Fundamentos de Programación | D10: 3 | E10: Complementaria | F10: Desarrollo de software – técnica | G10: Programación y resolución de problemas mediante código | H10: Contenidos técnicos de programación propios del curso | I10: Nula | J10: Baja | K10: Baja | L10: Baja | M10: — | N10: — | O10: No encaja | P10: Baja | Q10: No requiere simulador — asignatura sin decisiones de gestión, proyecto o negocio | R10: Ninguno | S10: Competencia técnica individual; no hay decisiones de gestión ni dinámica de equipo formalizada. Forzar un simulador aquí restaría credibilidad a la propuesta. | T10: No aplica | U10: Baja | V10: Inferencia académica
A11: Ingeniería Electrónica | B11: Semestre 1 | C11: Fundamentos de Electrónica | D11: 2 | E11: Complementaria | F11: Electrónica, hardware e infraestructura | G11: Diseño y operación de sistemas electrónicos y de infraestructura | H11: Contenidos técnicos propios del curso | I11: Nula | J11: Baja | K11: Baja | L11: Baja | M11: — | N11: — | O11: No encaja | P11: Baja | Q11: No requiere simulador — asignatura sin decisiones de gestión, proyecto o negocio | R11: Ninguno | S11: Dominio técnico sin decisiones de gestión, proyecto o negocio. | T11: No aplica | U11: Baja | V11: Inferencia académica
A12: Ingeniería Electrónica | B12: Semestre 1 | C12: Inglés I | D12: 2 | E12: Complementaria | F12: Formación complementaria – idioma | G12: Competencia comunicativa en inglés | H12: Comprensión y producción oral y escrita en inglés | I12: Nula | J12: Baja | K12: Baja | L12: Baja | M12: — | N12: — | O12: No encaja | P12: Baja | Q12: No requiere simulador — asignatura sin decisiones de gestión, proyecto o negocio | R12: Ninguno | S12: Curso de idioma sin contenidos de gestión. | T12: No aplica | U12: Baja | V12: Inferencia académica
A13: Ingeniería Electrónica | B13: Semestre 2 | C13: Álgebra Lineal | D13: 3 | E13: Ciencias Básicas | F13: Ciencias básicas – matemáticas | G13: Razonamiento matemático y modelado cuantitativo | H13: Contenidos matemáticos propios del curso | I13: Nula | J13: Baja | K13: Baja | L13: Baja | M13: — | N13: — | O13: No encaja | P13: Baja | Q13: No requiere simulador — asignatura sin decisiones de gestión, proyecto o negocio | R13: Ninguno | S13: Asignatura de ciencias básicas sin decisiones de gestión, proyecto o negocio. | T13: No aplica | U13: Baja | V13: Inferencia académica
A14: Ingeniería Electrónica | B14: Semestre 2 | C14: Física Mecánica | D14: 4 | E14: Ciencias Básicas | F14: Ciencias básicas – física | G14: Modelado físico de sistemas y experimentación | H14: Contenidos físicos propios del curso; trabajo de laboratorio | I14: Nula para simuladores de gestión | J14: Baja | K14: Baja | L14: Baja | M14: — | N14: — | O14: No encaja | P14: Media | Q14: Laboratorio virtual de física (línea de producto distinta a los simuladores de gestión) | R14: Ninguno | S14: Sin relación con simuladores de gestión. La única oportunidad es de laboratorio virtual, que es una línea de producto distinta. | T14: No aplica | U14: Baja | V14: Inferencia académica
A15: Ingeniería Electrónica | B15: Semestre 2 | C15: Cálculo | D15: 4 | E15: Ciencias Básicas de Ingeniería | F15: Ciencias básicas – matemáticas | G15: Razonamiento matemático y modelado cuantitativo | H15: Contenidos matemáticos propios del curso | I15: Nula | J15: Baja | K15: Baja | L15: Baja | M15: — | N15: — | O15: No encaja | P15: Baja | Q15: No requiere simulador — asignatura sin decisiones de gestión, proyecto o negocio | R15: Ninguno | S15: Asignatura de ciencias básicas sin decisiones de gestión, proyecto o negocio. | T15: No aplica | U15: Baja | V15: Inferencia académica
A16: Ingeniería Electrónica | B16: Semestre 2 | C16: Programación Orientada a Objetos | D16: 3 | E16: Ciencias Básicas de Ingeniería | F16: Desarrollo de software – técnica | G16: Programación y resolución de problemas mediante código | H16: Contenidos técnicos de programación propios del curso | I16: Nula | J16: Baja | K16: Baja | L16: Baja | M16: — | N16: — | O16: No encaja | P16: Baja | Q16: No requiere simulador — asignatura sin decisiones de gestión, proyecto o negocio | R16: Ninguno | S16: Competencia técnica individual; no hay decisiones de gestión ni dinámica de equipo formalizada. Forzar un simulador aquí restaría credibilidad a la propuesta. | T16: No aplica | U16: Baja | V16: Inferencia académica
... A62: Ingeniería Electrónica | B62: Semestre 8 | C62: Inglés VIII | D62: 2 | E62: Complementaria | F62: Formación complementaria – idioma | G62: Competencia comunicativa en inglés | H62: Comprensión y producción oral y escrita en inglés | I62: Nula | J62: Baja | K62: Baja | L62: Baja | M62: — | N62: — | O62: No encaja | P62: Baja | Q62: No requiere simulador — asignatura sin decisiones de gestión, proyecto o negocio | R62: Ninguno | S62: Curso de idioma sin contenidos de gestión. | T62: No aplica | U62: Baja | V62: Inferencia académica
A64: Nota: Explícito en la lámina → programa, semestre, asignatura, créditos y componente de formación. Inferencia académica → área temática, competencias, temáticas, relación con la gestión y todos los niveles de compatibilidad. Grado de ajuste CompanyGame: Encaje perfecto = el simulador cubre el objeto central del curso; Encaje parcial = cubre una unidad o el contexto; No encaja = ningún simulador del catálogo aplica.

Sheet Biológica
A1: Matriz de relacionamiento – Ingeniería Biológica
A2: Universidad de San Buenaventura – Facultad de Ingeniería · SNIES 3828 · 8 semestres · 55 espacios académicos · 144 créditos
A4: Programa | B4: Semestre | C4: Asignatura | D4: Créditos | E4: Componente de formación | F4: Área temática | G4: Competencias principales | H4: Temáticas principales | I4: Relación con gestión / negocio | J4: SimVenture | K4: SimAgile | L4: SimProject | M4: Simulador CompanyGame que encaja | N4: Nivel CG | O4: Grado de ajuste | P4: Desarrollo propio | Q4: Tipo de simulador que se requeriría | R4: Simulador recomendado | S4: Justificación de la recomendación | T4: Tipo de uso sugerido | U4: Prioridad comercial | V4: Origen de competencias y temáticas
A5: Ingeniería Biológica | B5: Semestre 1 | C5: Cálculo I | D5: 4 | E5: No disponible en la fuente | F5: Ciencias básicas – matemáticas | G5: Razonamiento matemático y modelado cuantitativo | H5: Contenidos matemáticos propios del curso | I5: Nula | J5: Baja | K5: Baja | L5: Baja | M5: — | N5: — | O5: No encaja | P5: Baja | Q5: No requiere simulador — asignatura sin decisiones de gestión, proyecto o negocio | R5: Ninguno | S5: Asignatura de ciencias básicas sin decisiones de gestión, proyecto o negocio. | T5: No aplica | U5: Baja | V5: Inferencia académica
A6: Ingeniería Biológica | B6: Semestre 1 | C6: Química General | D6: 3 | E6: No disponible en la fuente | F6: Ciencias básicas – química | G6: Fundamentos químicos y trabajo experimental | H6: Contenidos químicos propios del curso; prácticas de laboratorio | I6: Nula para simuladores de gestión | J6: Baja | K6: Baja | L6: Baja | M6: — | N6: — | O6: No encaja | P6: Media | Q6: Laboratorio virtual de química (línea de producto distinta a los simuladores de gestión) | R6: Ninguno | S6: Sin relación con simuladores de gestión; oportunidad únicamente en laboratorio virtual. | T6: No aplica | U6: Baja | V6: Inferencia académica
A7: Ingeniería Biológica | B7: Semestre 1 | C7: Biología Celular | D7: 3 | E7: No disponible en la fuente | F7: Ciencias básicas – biología y bioprocesos | G7: Fundamentos biológicos aplicados a la ingeniería | H7: Contenidos biológicos y de bioprocesos propios del curso | I7: Nula para simuladores de gestión | J7: Baja | K7: Baja | L7: Baja | M7: — | N7: — | O7: No encaja | P7: Media | Q7: Laboratorio o simulador virtual de bioprocesos (línea de producto distinta) | R7: Ninguno | S7: Contenido científico-técnico sin decisiones de gestión. La oportunidad sería un laboratorio o simulador de bioprocesos, línea distinta a los simuladores de negocio. | T7: No aplica | U7: Baja | V7: Inferencia académica
A8: Ingeniería Biológica | B8: Semestre 1 | C8: Introducción a la Ingeniería | D8: 3 | E8: No disponible en la fuente | F8: Fundamentación profesional | G8: Comprensión del campo de acción del ingeniero; trabajo en equipo | H8: Perfil profesional, campos de la ingeniería, rol del ingeniero | I8: Media - contextualización profesional | J8: Baja | K8: Baja | L8: Baja | M8: — | N8: — | O8: No encaja | P8: Media | Q8: Cubierto parcialmente por el catálogo; el resto del curso se apoya en SimVenture, SimAgile o SimProject | R8: T-Shirt / Sunny Day (CompanyGame, nivel introductorio) | S8: Curso de contextualización sin decisiones de gestión, pero un simulador CompanyGame de nivel 1-2 funciona como primera experiencia de decisión empresarial en primer semestre. Está en los siete programas de la facultad, lo que lo convierte en la entrada de mayor volumen de estudiantes de toda la propuesta. | T8: Exploratorio | U8: Media | V8: Inferencia académica
A9: Ingeniería Biológica | B9: Semestre 1 | C9: Humanística I | D9: 2 | E9: No disponible en la fuente | F9: Formación humanística | G9: Formación humanística, ética y ciudadana | H9: Contenidos humanísticos propios del curso | I9: Baja | J9: Baja | K9: Baja | L9: Baja | M9: — | N9: — | O9: No encaja | P9: Baja | Q9: No requiere simulador — asignatura sin decisiones de gestión, proyecto o negocio | R9: Ninguno | S9: Formación humanística sin contenidos de gestión que justifiquen un simulador. | T9: No aplica | U9: Baja | V9: Inferencia académica
A10: Ingeniería Biológica | B10: Semestre 1 | C10: Comunicación Oral y Escrita I | D10: 1 | E10: No disponible en la fuente | F10: Formación humanística | G10: Formación humanística, ética y ciudadana | H10: Contenidos humanísticos propios del curso | I10: Baja | J10: Baja | K10: Baja | L10: Baja | M10: — | N10: — | O10: No encaja | P10: Baja | Q10: No requiere simulador — asignatura sin decisiones de gestión, proyecto o negocio | R10: Ninguno | S10: Formación humanística sin contenidos de gestión que justifiquen un simulador. | T10: No aplica | U10: Baja | V10: Inferencia académica
A11: Ingeniería Biológica | B11: Semestre 1 | C11: Inglés I | D11: 2 | E11: No disponible en la fuente | F11: Formación complementaria – idioma | G11: Competencia comunicativa en inglés | H11: Comprensión y producción oral y escrita en inglés | I11: Nula | J11: Baja | K11: Baja | L11: Baja | M11: — | N11: — | O11: No encaja | P11: Baja | Q11: No requiere simulador — asignatura sin decisiones de gestión, proyecto o negocio | R11: Ninguno | S11: Curso de idioma sin contenidos de gestión. | T11: No aplica | U11: Baja | V11: Inferencia académica
A12: Ingeniería Biológica | B12: Semestre 2 | C12: Cálculo II | D12: 3 | E12: No disponible en la fuente | F12: Ciencias básicas – matemáticas | G12: Razonamiento matemático y modelado cuantitativo | H12: Contenidos matemáticos propios del curso | I12: Nula | J12: Baja | K12: Baja | L12: Baja | M12: — | N12: — | O12: No encaja | P12: Baja | Q12: No requiere simulador — asignatura sin decisiones de gestión, proyecto o negocio | R12: Ninguno | S12: Asignatura de ciencias básicas sin decisiones de gestión, proyecto o negocio. | T12: No aplica | U12: Baja | V12: Inferencia académica
A13: Ingeniería Biológica | B13: Semestre 2 | C13: Álgebra Lineal | D13: 3 | E13: No disponible en la fuente | F13: Ciencias básicas – matemáticas | G13: Razonamiento matemático y modelado cuantitativo | H13: Contenidos matemáticos propios del curso | I13: Nula | J13: Baja | K13: Baja | L13: Baja | M13: — | N13: — | O13: No encaja | P13: Baja | Q13: No requiere simulador — asignatura sin decisiones de gestión, proyecto o negocio | R13: Ninguno | S13: Asignatura de ciencias básicas sin decisiones de gestión, proyecto o negocio. | T13: No aplica | U13: Baja | V13: Inferencia académica
A14: Ingeniería Biológica | B14: Semestre 2 | C14: Biología Vegetal y Animal | D14: 3 | E14: No disponible en la fuente | F14: Ciencias básicas – biología y bioprocesos | G14: Fundamentos biológicos aplicados a la ingeniería | H14: Contenidos biológicos y de bioprocesos propios del curso | I14: Nula para simuladores de gestión | J14: Baja | K14: Baja | L14: Baja | M14: — | N14: — | O14: No encaja | P14: Media | Q14: Laboratorio o simulador virtual de bioprocesos (línea de producto distinta) | R14: Ninguno | S14: Contenido científico-técnico sin decisiones de gestión. La oportunidad sería un laboratorio o simulador de bioprocesos, línea distinta a los simuladores de negocio. | T14: No aplica | U14: Baja | V14: Inferencia académica
A15: Ingeniería Biológica | B15: Semestre 2 | C15: Física | D15: 4 | E15: No disponible en la fuente | F15: Ciencias básicas – física | G15: Modelado físico de sistemas y experimentación | H15: Contenidos físicos propios del curso; trabajo de laboratorio | I15: Nula para simuladores de gestión | J15: Baja | K15: Baja | L15: Baja | M15: — | N15: — | O15: No encaja | P15: Media | Q15: Laboratorio virtual de física (línea de producto distinta a los simuladores de gestión) | R15: Ninguno | S15: Sin relación con simuladores de gestión. La única oportunidad es de laboratorio virtual, que es una línea de producto distinta. | T15: No aplica | U15: Baja | V15: Inferencia académica
A16: Ingeniería Biológica | B16: Semestre 2 | C16: Fundamentos de Programación | D16: 3 | E16: No disponible en la fuente | F16: Desarrollo de software – técnica | G16: Programación y resolución de problemas mediante código | H16: Contenidos técnicos de programación propios del curso | I16: Nula | J16: Baja | K16: Baja | L16: Baja | M16: — | N16: — | O16: No encaja | P16: Baja | Q16: No requiere simulador — asignatura sin decisiones de gestión, proyecto o negocio | R16: Ninguno | S16: Competencia técnica individual; no hay decisiones de gestión ni dinámica de equipo formalizada. Forzar un simulador aquí restaría credibilidad a la propuesta. | T16: No aplica | U16: Baja | V16: Inferencia académica
... A59: Ingeniería Biológica | B59: Semestre 8 | C59: Inglés VIII | D59: 2 | E59: No disponible en la fuente | F59: Formación complementaria – idioma | G59: Competencia comunicativa en inglés | H59: Comprensión y producción oral y escrita en inglés | I59: Nula | J59: Baja | K59: Baja | L59: Baja | M59: — | N59: — | O59: No encaja | P59: Baja | Q59: No requiere simulador — asignatura sin decisiones de gestión, proyecto o negocio | R59: Ninguno | S59: Curso de idioma sin contenidos de gestión. | T59: No aplica | U59: Baja | V59: Inferencia académica
A61: Nota: Explícito en la lámina → programa, semestre, asignatura, créditos y componente de formación. Inferencia académica → área temática, competencias, temáticas, relación con la gestión y todos los niveles de compatibilidad. Grado de ajuste CompanyGame: Encaje perfecto = el simulador cubre el objeto central del curso; Encaje parcial = cubre una unidad o el contexto; No encaja = ningún simulador del catálogo aplica.

Sheet Priorización
A1: Priorización comercial de oportunidades
A2: Universidad de San Buenaventura · ranking de espacios académicos con mayor potencial de implementación
A4: Ranking | B4: Bloque | C4: Programa(s) donde aparece | D4: N.º de programas | E4: Semestre | F4: Créditos | G4: Asignatura | H4: Simulador recomendado | I4: Simulador CompanyGame que encaja | J4: Grado de ajuste | K4: ¿Por qué es una oportunidad? | L4: Argumento para la conversación comercial
A5: 1 | B5: Top 15 | C5: Sistemas | D5: 1 | E5: S7 | F5: 3C | G5: Cátedra de Emprendimiento | H5: SimVenture o la familia Emprendimiento de CompanyGame | I5: FitnessGym / Luxe Atelier / Business Chef | J5: Encaje perfecto | K5: Es la asignatura de encaje más natural de todo el portafolio: emprender es literalmente lo que el simulador hace hacer al estudiante. Además es el único espacio de emprendimiento de los siete programas de la facultad, lo que la convierte en la puerta de entrada de la familia Emprendimiento de CompanyGame. | L5: Es la conversación más corta de toda la facultad: el curso ya se llama como lo que hace el simulador. Único espacio de emprendimiento en los siete programas, así que es la puerta de entrada obligada de la familia Emprendimiento del catálogo.
A6: 2 | B6: Top 15 | C6: Industrial · Agroindustrial · Biológica | D6: 3 | E6: S5, S6 | F6: 3C | G6: Gerencia de Proyectos de Ingeniería | H6: SimProject | I6: Acelera | J6: Encaje parcial | K6: El temario de dirección de proyectos coincide punto por punto con las decisiones que exige SimProject: alcance, cronograma, recursos, costos, riesgos y control. El catálogo CompanyGame no tiene un simulador específico de dirección de proyectos, por lo que aquí SimProject no tiene sustituto interno. | L6: Está en tres programas (Industrial, Agroindustrial y Biológica) con el mismo nombre y probablemente con docentes compartidos: una sola demostración puede cerrar tres cursos.
A7: 3 | B7: Top 15 | C7: Industrial | D7: 1 | E7: S4 | F7: 2C | G7: Gestión Estratégica Organizacional | H7: SimVenture o Business21 / Businessglobal (CompanyGame) | I7: Business21 / Businessglobal | J7: Encaje perfecto | K7: Es la asignatura de estrategia del programa: el estudiante debe formular una estrategia y sostenerla frente a competidores durante varios períodos, que es exactamente lo que hace el simulador. Con 2 créditos conviene proponer un simulador de nivel intermedio (Business21) antes que uno de nivel 5. | L7: Argumento directo: hoy la estrategia se evalúa por documento; con el simulador se evalúa por desempeño sostenido frente a competidores. Con 2 créditos conviene ofrecer Business21 antes que un nivel 5.
A8: 4 | B8: Top 15 | C8: Industrial · Agroindustrial | D8: 2 | E8: S5 | F8: 3C | G8: Ingeniería Económica | H8: SimVenture + SimProject o Kapital (CompanyGame) | I8: Kapital | J8: Encaje perfecto | K8: El VPN y la TIR dejan de ser cálculo de escritorio y pasan a ser resultado de decisiones tomadas con recursos limitados. SimProject aporta la evaluación económica dentro de un proyecto con restricciones de tiempo y costo. | L8: Está en Industrial y Agroindustrial. Requiere mostrar los reportes financieros del simulador; con una demostración de 20 minutos la objeción desaparece.
A9: 5 | B9: Top 15 | C9: Industrial · Biológica | D9: 2 | E9: S4 | F9: 2, 3C | G9: Ingeniería de Costos | H9: SimVenture o ContaTrainer (CompanyGame) | I9: ContaTrainer / Kapital | J9: Encaje perfecto | K9: Cada decisión del simulador modifica la estructura de costos y el punto de equilibrio, de modo que el costeo se vuelve consecuencia visible de la decisión y no un ejercicio de hoja de cálculo. | L9: Está en Industrial y Biológica. Se vende mejor como paquete con Ingeniería Económica que como caso aislado.
A10: 6 | B10: Top 15 | C10: Sistemas | D10: 1 | E10: S9 | F10: 3C | G10: Evaluación de Proyectos de Software | H10: SimVenture + SimProject; alternativa CompanyGame: familia Emprendimiento | I10: FitnessGym / Business Chef | J10: Encaje perfecto | K10: Encaje alto simultáneo en dos simuladores: SimVenture cubre la viabilidad comercial y financiera del proyecto, SimProject la planeación y el control de su ejecución. Permite proponer un paquete de dos productos en un solo curso. | L10: Permite proponer dos productos en un mismo curso con justificación académica distinta para cada uno.
A11: 7 | B11: Top 15 | C11: Industrial | D11: 1 | E11: S6 | F11: 3C | G11: Diseño de Productos y Servicios | H11: SimAgile (principal) + SimVenture o InnovaTech (CompanyGame) | I11: InnovaTech | J11: Encaje perfecto | K11: El desarrollo de producto moderno es iterativo y basado en validación, que es el modelo de SimAgile; InnovaTech es la alternativa CompanyGame más ajustada y SimVenture agrega la prueba de viabilidad comercial. Doble encaje poco frecuente, muy útil para proponer un paquete. | L11: Permite introducir SimAgile en un programa de industrial, donde normalmente sólo se conversa sobre SimVenture.
A12: 8 | B12: Top 15 | C12: Biomédica | D12: 1 | E12: S7 | F12: 3C | G12: Valoración de Proyectos | H12: SimVenture + SimProject; alternativa CompanyGame: familia Emprendimiento | I12: FitnessGym / Business Chef | J12: Encaje perfecto | K12: Encaje alto simultáneo en dos simuladores: SimVenture cubre la viabilidad comercial y financiera del proyecto, SimProject la planeación y el control de su ejecución. Permite proponer un paquete de dos productos en un solo curso. | L12: Es la asignatura de negocio de Biomédica, un programa donde el portafolio no tiene otra entrada natural.
A13: 9 | B13: Top 15 | C13: Electrónica | D13: 1 | E13: S7 | F13: 2C | G13: Gestión de Productos Tecnológicos | H13: SimAgile (principal) + SimVenture o InnovaTech (CompanyGame) | I13: InnovaTech | J13: Encaje perfecto | K13: El desarrollo de producto moderno es iterativo y basado en validación, que es el modelo de SimAgile; InnovaTech es la alternativa CompanyGame más ajustada y SimVenture agrega la prueba de viabilidad comercial. Doble encaje poco frecuente, muy útil para proponer un paquete. | L13: Es la única asignatura de gestión de Electrónica: entrar por aquí es la forma de existir en ese programa.
A14: 10 | B14: Top 15 | C14: Sistemas | D14: 1 | E14: S7 | F14: 2C | G14: Gestión de Proyectos de Software | H14: SimAgile (principal) + SimProject (complementario) | I14: Organization & People Management | J14: Encaje parcial | K14: Doble encaje en un mismo curso: SimAgile aporta la dinámica de equipo y la entrega incremental, SimProject el control de alcance, tiempo y costo. El estudiante experimenta la tensión entre alcance, calidad y tiempo en lugar de estudiarla en teoría. | L14: El docente de esta asignatura suele ser también el de los proyectos de diseño de software, lo que concentra la decisión en un solo interlocutor dentro del programa.
A15: 11 | B15: Top 15 | C15: Industrial | D15: 1 | E15: S5 | F15: 2C | G15: Investigación de Mercados | H15: SimVenture o MarketGame / SalesManager (CompanyGame) | I15: MarketGame / SalesManager | J15: Encaje perfecto | K15: El resultado comercial se mide en ventas y participación de mercado frente a competidores del aula, no en un plan de mercadeo escrito. La familia Marketing y ventas de CompanyGame ofrece cuatro niveles para ajustar la propuesta al presupuesto del programa. | L15: Es la aplicación más reconocible de un simulador de negocios; casi no requiere explicación previa. En Agroindustrial aparece como Mercadeo e Investigación de Mercados.
A16: 12 | B16: Top 15 | C16: Agroindustrial | D16: 1 | E16: S4 | F16: 2C | G16: Mercadeo e Investigación de Mercados | H16: SimVenture o MarketGame / SalesManager (CompanyGame) | I16: MarketGame / SalesManager | J16: Encaje perfecto | K16: El resultado comercial se mide en ventas y participación de mercado frente a competidores del aula, no en un plan de mercadeo escrito. La familia Marketing y ventas de CompanyGame ofrece cuatro niveles para ajustar la propuesta al presupuesto del programa. | L16: Oportunidad de segundo nivel: conviene incluirla dentro de un acuerdo de programa y no venderla de forma aislada.
... A29: 25 | B29: Siguiente nivel | C29: Sistemas | D29: 1 | E29: S5 | F29: 3C | G29: Ingeniería de Requisitos | H29: SimAgile | I29: Organization & People Management | J29: Encaje parcial | K29: Es donde se enseñan los marcos ágiles: SimAgile permite que el estudiante viva un ciclo completo de trabajo en equipo en lugar de memorizar roles y ceremonias. Encaje directo con una unidad completa del curso. | L29: Oportunidad de segundo nivel: conviene incluirla dentro de un acuerdo de programa y no venderla de forma aislada.
A31: Cada fila es una conversación comercial, no una asignatura: cuando la misma asignatura aparece en varios programas se agrupa en una sola línea. Criterio de ordenamiento: nivel de encaje con el temario (Alta > Media), grado de ajuste con el catálogo CompanyGame, número de programas donde aparece la asignatura, créditos y existencia de producto listo para usar.

Sheet Desarrollos Propios
A1: Oportunidades de desarrollo propio de simuladores
A2: Asignaturas sin cobertura de SimVenture, SimAgile, SimProject ni del catálogo CompanyGame, priorizadas por transversalidad entre asignaturas y programas
A4: Código | B4: Simulador propuesto | C4: Programa(s) | D4: Problema o necesidad académica que resuelve | E4: Temática que debería simular | F4: Decisiones que debería permitir tomar al estudiante | G4: Competencias que permitiría desarrollar | H4: Por qué conviene un desarrollo propio y no un simulador existente | I4: Transversalidad | J4: Prioridad
A5: DP-01 | B5: Simulador de Planeación y Control de Operaciones | C5: Ing. Industrial · Ing. Agroindustrial · Ing. Biológica | D5: El núcleo productivo de tres programas (Gestión de Operaciones, Investigación de Operaciones, Ingeniería de Métodos y Tiempos, Simulación de Procesos Discretos, Localización y Diseño de Plantas, Procesos Agroindustriales I y II, Ingeniería de Procesos Biológicos I y II) no tiene ningún simulador aplicable, ni propio ni del catálogo CompanyGame. | E5: Una planta con demanda variable: pronóstico, plan de producción, capacidad, inventarios y programación. | F5: Nivel de producción por período; tamaño de lote; turnos y contratación; inventario de seguridad; subcontratación; inversión en capacidad. | G5: Planeación y control de operaciones; gestión de inventarios; análisis del trade-off costo-nivel de servicio; decisión bajo demanda incierta. | H5: SimVenture y Businessglobal modelan la producción de forma agregada, muy por debajo del nivel de estos cursos. Es el mayor vacío del portafolio frente a la Facultad de Ingeniería de San Buenaventura y el desarrollo con más asignaturas destino. | I5: Muy alta - 9 asignaturas en 3 programas | J5: Prioridad 1
A6: DP-03 | B6: Simulador de Implementación y Auditoría de Sistemas de Gestión de Calidad | C6: Ing. Industrial · Ing. Agroindustrial | D6: Gestión de Calidad existe con el mismo nombre en dos programas y se enseña leyendo la norma: el estudiante no experimenta el costo, la resistencia interna ni el resultado de una auditoría. | E6: Implementación de un sistema de gestión: diagnóstico, documentación, capacitación, auditoría interna y certificación. | F6: Qué procesos documentar primero; presupuesto y equipo asignado; profundidad de la capacitación; tratamiento de no conformidades; momento de solicitar la certificación. | G6: Gestión por procesos; planeación de la implementación; auditoría interna; mejora continua. | H6: Del catálogo CompanyGame sólo ESGManagement toca de forma parcial la dimensión ambiental y social; el contenido normativo y de auditoría, que es el núcleo del curso, no está cubierto por ningún producto. | I6: Alta - 2 asignaturas en 2 programas, más Control Estadístico de Procesos | J6: Prioridad 1
A7: DP-05 | B7: Simulador de Gestión de Incidentes de Seguridad de la Información | C7: Ing. de Sistemas | D7: Seguridad Informática se enseña desde el control y la norma, sin experiencia de decisión bajo presión de tiempo ante un incidente real. | E7: Una organización que sufre incidentes: detección, contención, comunicación, recuperación y aprendizaje. | F7: Inversión en controles preventivos frente a controles de detección; a quién y cuándo comunicar; aislar o mantener el servicio; prioridad de recuperación. | G7: Análisis y tratamiento del riesgo; respuesta a incidentes; continuidad del negocio; comunicación de crisis. | H7: Ningún simulador del portafolio ni del catálogo aborda seguridad. El tema tiene alta demanda institucional y prácticamente no hay oferta en español, lo que lo hace muy defendible comercialmente. | I7: Media - 1 asignatura, pero de alta visibilidad institucional | J7: Prioridad 2
A8: DP-04 | B8: Simulador de Cadena de Suministro | C8: Ing. Industrial · Ing. Agroindustrial | D8: Gestión Cadena Abastecimiento exige comprender el efecto látigo y la coordinación entre eslabones, algo que no se enseña con ejercicios individuales de inventario. | E8: Una cadena de varios eslabones con demanda variable, tiempos de entrega y costos de faltante. | F8: Cantidad y momento de pedido; selección de proveedores; nivel de servicio objetivo; modo de transporte; información compartida entre eslabones. | G8: Gestión de inventarios; coordinación de la cadena; trade-off costo-servicio; decisión con información incompleta. | H8: SimVenture y Businessglobal incluyen compras e inventarios dentro de una sola empresa; ninguno modela la cadena ni la interacción entre eslabones, que es el aprendizaje central del curso. | I8: Media - 1 asignatura directa y 3 relacionadas | J8: Prioridad 2
A9: DP-12 | B9: Simulador de Gestión de Tecnología Hospitalaria | C9: Ing. Biomédica | D9: Ingeniería Clínica I y II son las únicas asignaturas de gestión del programa y hoy no tienen ninguna herramienta de decisión asociada. Sin este desarrollo, Biomédica queda prácticamente fuera del portafolio. | E9: Un servicio de ingeniería clínica: parque de equipos médicos, mantenimiento, disponibilidad y presupuesto. | F9: Qué tecnología adquirir y cuándo renovarla; mantenimiento preventivo frente a correctivo; nivel de disponibilidad objetivo; asignación del presupuesto entre servicios. | G9: Gestión de activos tecnológicos; planeación del mantenimiento; análisis costo-disponibilidad; gestión presupuestal en una institución de salud. | H9: Ningún simulador del portafolio ni del catálogo modela la gestión de tecnología en salud. Es un nicho con muy poca competencia y aplicable también a programas de administración en salud de otras universidades. | I9: Media - 2 asignaturas, pero es la única entrada al programa | J9: Prioridad 2
A10: DP-11 | B10: Simulador de Gestión de una Producción Audiovisual o Multimedia | C10: Ing. Multimedia | D10: La malla de Multimedia es creativa y técnica: sólo Gestión en Proyectos y Proyecto en Ingeniería tienen componente de gestión. Los talleres de producción no tienen ninguna herramienta de decisión. | E10: Una producción audiovisual o interactiva: presupuesto, cronograma, equipo creativo, cliente y alcance. | F10: Composición del equipo; asignación de presupuesto entre etapas; manejo de cambios de alcance del cliente; calidad frente a fecha de entrega; derechos y licenciamiento. | G10: Gestión de proyectos creativos; presupuestación; negociación de alcance con el cliente; trabajo en equipo multidisciplinar. | H10: SimProject cubre la lógica de proyecto pero no el contexto creativo ni la relación con el cliente, que es lo que hace reconocible el curso para el docente de Multimedia. | I10: Media - 3 a 4 asignaturas de un programa | J10: Prioridad 3
A11: DP-13 | B11: Simulador de Digitalización de una Operación Agropecuaria | C11: Ing. Agroindustrial · Ing. Biológica | D11: GestiónDigital de Sistemas Agropecuarios y Agricultura Regenerativa tratan la adopción de tecnología en el campo sin ninguna experiencia de decisión. | E11: Una operación agropecuaria que incorpora tecnología: sensores, datos, trazabilidad y prácticas sostenibles. | F11: Qué tecnología adoptar y en qué orden; inversión frente a retorno esperado; manejo del recurso hídrico y del suelo; trazabilidad y certificaciones. | G11: Adopción tecnológica; decisión de inversión en el agro; sostenibilidad de la operación; uso de datos. | H11: TRANSFORMA y Global2030 cubren la transformación digital de forma genérica; el contexto agropecuario, que es lo que hace pertinente el curso, no está modelado. | I11: Media - 3 asignaturas en 2 programas | J11: Prioridad 3
A12: DP-06 | B12: Simulador de Control Estadístico de Procesos | C12: Ing. Industrial | D12: El control estadístico se enseña sobre series de datos dadas; el estudiante nunca decide cuándo intervenir un proceso ni asume el costo de equivocarse. | E12: Un proceso con variabilidad natural y causas asignables: muestreo, cartas de control y costo de la no calidad. | F12: Tamaño y frecuencia del muestreo; cuándo intervenir el proceso; nivel de inspección; inversión en mejora. | G12: Control estadístico de procesos; análisis de capacidad; decisión bajo variabilidad; costeo de la calidad. | H12: Ningún simulador de gestión, ni propio ni del catálogo, modela variabilidad de proceso. Desarrollo acotado, de complejidad media, reutilizable con el motor de DP-01. | I12: Baja - 1 asignatura, complementaria de DP-01 y DP-03 | J12: Prioridad 3
A13: DP-07 | B13: Simulador de Dilemas Éticos en la Decisión Profesional | C13: Todos los programas | D13: Ética, Ética en Ingeniería Biológica y los espacios franciscanos se enseñan de forma discursiva; no hay instrumento que muestre la consecuencia de una decisión cuestionable en el tiempo. | E13: Decisiones profesionales con tensión entre resultado económico, impacto ambiental y consecuencias éticas. | F13: Aceptar o rechazar prácticas rentables pero cuestionables; nivel de transparencia; inversión en mitigación; reporte de un hallazgo incómodo. | G13: Razonamiento ético aplicado; análisis de impacto; responsabilidad profesional. | H13: La familia ESG Management cubre la dimensión de sostenibilidad y debe ofrecerse primero; el dilema ético profesional propiamente dicho no lo aborda ningún producto. Desarrollo de baja complejidad, basado en escenarios. | I13: Media - presente en los 7 programas, con baja complejidad de desarrollo | J13: Prioridad 3
A14: DP-10 | B14: Línea de laboratorios virtuales (producto distinto a simuladores de gestión) | C14: Todos los programas | D14: Las asignaturas de física, química, biología y electrónica dependen de infraestructura física, insumos y disponibilidad de espacio, con limitaciones de cupo y de repetición de la práctica. | E14: Prácticas experimentales de física, química, biología, bioprocesos y electrónica. | F14: Montaje experimental; variación de parámetros; repetición de mediciones; interpretación de resultados. | G14: Competencia experimental; manejo de instrumentos; análisis de datos experimentales. | H14: Se registra por completitud del análisis: no es una oportunidad para simuladores de gestión sino para una línea de producto distinta, con otro interlocutor y otro presupuesto dentro de la universidad. | I14: Alta en número de asignaturas, pero corresponde a otra línea de producto | J14: Fuera del alcance de simuladores de gestión

Sheet Recomendaciones
A1: Ruta de implementación y recomendaciones estratégicas
A2: Insumo para la conversación con el decano de Ingeniería y los directores de los siete programas
A4: Conclusión por programa
A5: Ingeniería Industrial | B5: Programa de mayor potencial de la facultad. SimVenture y las familias Negocios y estrategia y Finanzas del catálogo cubren Gestión Estratégica Organizacional (4), Ingeniería de Costos (4), Ingeniería Económica (5) e Investigación de Mercados (5); SimAgile entra por Diseño de Productos y Servicios (6) e InnovaTech; SimProject por Gerencia de Proyectos de Ingeniería (6) y los dos Diseño en Ingeniería Industrial. La línea de operaciones (Gestión de Operaciones, Cadena de Abastecimiento, Métodos y Tiempos, Localización de Plantas, Simulación de Procesos Discretos, Control Estadístico) no tiene cobertura y es el destino del desarrollo propio DP-01.
A6: Ingeniería de Sistemas | B6: Terreno de SimAgile y SimProject, con la línea de software recorriendo siete semestres. Cátedra de Emprendimiento (7) es el mejor encaje individual de toda la facultad para SimVenture y para la familia Emprendimiento. Seguridad Informática (8) es la mejor candidata a desarrollo propio del programa. El componente técnico de programación, bases de datos y redes no ofrece oportunidad y no debe forzarse. La lámina de este programa no publica componentes de formación.
A7: Ingeniería Multimedia | B7: Encaje limitado y concentrado: Gestión en Proyectos (6) y Proyecto en Ingeniería (7) son las dos entradas reales para SimProject; Diseño de Medios Digitales y Diseño de Experiencias Interactivas admiten SimAgile de forma parcial. El resto de la malla es producción creativa y técnica. La oportunidad diferenciadora es un simulador propio de gestión de producción audiovisual (DP-11).
A8: Ingeniería Agroindustrial | B8: Segundo programa en potencial. Mercadeo e Investigación de Mercados (4), Ingeniería Económica (5), Gerencia de Proyectos de Ingeniería (6) y Gestión de Calidad (7) son entradas claras; GestiónDigital de Sistemas Agropecuarios (4) abre la familia Business Transformation. Los procesos agroindustriales son destino del desarrollo propio DP-01 adaptado al sector.
A9: Ingeniería Biomédica | B9: Programa con el menor encaje del portafolio actual: sólo Valoración de Proyectos (7) e Ingeniería Clínica I y II (6 y 7) tienen componente de gestión, y Franciscanismo y Ecología (2) abre ESG. Sin un desarrollo propio de gestión de tecnología hospitalaria (DP-12), la conversación con este programa se agota rápido.
A10: Ingeniería Electrónica | B10: Una sola asignatura de gestión: Gestión de Productos Tecnológicos (7), con encaje perfecto con InnovaTech y alto con SimAgile. Prototipado de Soluciones Tecnológicas (6) y los dos Diseño de Ingeniería Electrónica complementan. Entrar por ahí y no forzar el resto de la malla, que es íntegramente técnica.
A11: Ingeniería Biológica | B11: Encaje moderado: Ingeniería de Costos (4), Gerencia de Proyectos de Ingeniería (5) y Analítica de Datos (7) son las entradas; Ecología Agrícola, Agricultura Regenerativa y Ética en Ingeniería Biológica abren la familia ESG. La lámina no publica componente de formación sino modalidad, por lo que esa columna queda vacía.
A13: Ruta de implementación
A14: Prioridad | B14: Asignatura o espacio curricular | C14: Semestre | D14: Simulador | E14: Acción sugerida | F14: Horizonte
A15: Prioridad 1 - Implementación inmediata | B15: CÁTEDRA DE EMPRENDIMIENTO | C15: S7 · Sistemas | D15: SimVenture o familia Emprendimiento (CompanyGame) | E15: Es el encaje más natural de toda la facultad y no requiere ninguna argumentación previa. Iniciar aquí. | F15: 0-6 meses
A16: Prioridad 1 - Implementación inmediata | B16: GERENCIA DE PROYECTOS DE INGENIERÍA | C16: S5-S6 · Industrial, Agroindustrial, Biológica | D16: SimProject | E16: Una sola demostración puede cerrar tres programas: misma asignatura, mismo nombre, posiblemente mismos docentes. | F16: 0-6 meses
A17: Prioridad 1 - Implementación inmediata | B17: GESTIÓN DE PROYECTOS DE SOFTWARE + PROYECTOS DE DISEÑO | C17: S6-S8 · Sistemas | D17: SimAgile + SimProject | E17: Paquete doble con el mismo docente de la línea de software. | F17: 0-6 meses
A18: Prioridad 1 - Implementación inmediata | B18: GESTIÓN ESTRATÉGICA ORGANIZACIONAL + INGENIERÍA DE COSTOS | C18: S4 · Industrial | D18: SimVenture o Business21 / ContaTrainer | E18: Vender la línea de gestión completa del programa, no la asignatura suelta. | F18: 0-6 meses
A19: Prioridad 1 - Implementación inmediata | B19: INGENIERÍA ECONÓMICA e INVESTIGACIÓN DE MERCADEO | C19: S4-S5 · Industrial y Agroindustrial | D19: SimVenture, Kapital o MarketGame | E19: Ampliar el acuerdo del programa hacia la línea financiera y comercial. | F19: 0-6 meses
A20: Prioridad 2 - Potencial de implementación | B20: DISEÑO DE PRODUCTOS Y SERVICIOS / GESTIÓN DE PRODUCTOS TECNOLÓGICOS | C20: S6-S7 · Industrial y Electrónica | D20: SimAgile o InnovaTech | E20: Puerta de entrada de SimAgile fuera de Sistemas; en Electrónica es la única entrada del programa. | F20: 6-12 meses
A21: Prioridad 2 - Potencial de implementación | B21: EVALUACIÓN DE PROYECTOS DE SOFTWARE / VALORACIÓN DE PROYECTOS | C21: S7-S9 · Sistemas y Biomédica | D21: SimVenture + SimProject | E21: Paquete doble; en Biomédica es la única asignatura de negocio del plan. | F21: 6-12 meses
A22: Prioridad 2 - Potencial de implementación | B22: FRANCISCANISMO Y ECOLOGÍA · ECOLOGÍA AGRÍCOLA · ÉTICA | C22: S2-S9 · varios programas | D22: ESGProject / ESGManagement (CompanyGame) | E22: Presentar como propuesta de facultad ligada al sello franciscano, no como venta de programa. | F22: 6-12 meses
A23: Prioridad 2 - Potencial de implementación | B23: INTRODUCCIÓN A LA INGENIERÍA | C23: S1 · los 7 programas | D23: T-Shirt o Sunny Day (CompanyGame) | E23: Entrada de mayor volumen de estudiantes de la facultad, con el menor costo de entrada. | F23: 6-12 meses
A24: Prioridad 2 - Potencial de implementación | B24: PRÁCTICA PROFESIONAL | C24: S7-S9 · los 7 programas | D24: SimVenture o Businessglobal | E24: Uso de preparación previa; baja resistencia docente, útil para abrir puerta en programas difíciles. | F24: 6-12 meses
A25: Prioridad 2 - Potencial de implementación | B25: ESPACIOS ELECTIVOS Y DE PROFUNDIZACIÓN | C25: varios · los 7 programas | D25: Según contenido | E25: 38 espacios electivos sin contenido definido: diseñar una electiva basada en simulador es la vía de inserción más rápida y no exige comité curricular. | F25: 6-12 meses
... A29: Prioridad 3 - Oportunidades de desarrollo propio | B29: INGENIERÍA CLÍNICA I y II | C29: S6-S7 · Biomédica | D29: DP-12 Tecnología hospitalaria | E29: Sin este desarrollo, Biomédica queda fuera del portafolio. | F29: 12-24 meses
A31: Recomendaciones para la conversación comercial
A32: • Entrar por CÁTEDRA DE EMPRENDIMIENTO en Ingeniería de Sistemas: es el encaje más natural de los siete programas y la conversación que menos argumentación requiere. Un piloto ahí genera el testimonio docente que sostiene todo lo demás.
A33: • Tratar GERENCIA DE PROYECTOS DE INGENIERÍA como una sola venta de facultad y no como tres ventas de programa: aparece con el mismo nombre en Industrial, Agroindustrial y Biológica.
A34: • Vender Ingeniería Industrial por líneas y no por asignaturas: la línea de gestión (semestres 4 a 7) admite SimVenture o Business21, Kapital, MarketGame e InnovaTech dentro de un mismo acuerdo.
A35: • Usar el escalonamiento por niveles del catálogo como argumento de continuidad: T-Shirt en primer semestre, Business21 en el ciclo intermedio y Businessglobal o Business Strategy en el ciclo profesional. Convierte una venta puntual en una ruta de varios años.
A36: • Llevar ESG por el lado del sello franciscano: Franciscanismo y Ecología, Ecología Agrícola y Agricultura Regenerativa son espacios donde ESGProject conecta con la identidad institucional de la universidad.
A37: • Aprovechar los 38 espacios electivos y de profundización de los siete programas: diseñar una electiva basada en simulador no exige modificar el plan de estudios ni pasar por comité curricular.
A38: • No ofrecer la familia HORECA a esta facultad y no forzar la oferta en ciencias básicas, laboratorios ni en las asignaturas técnicas de electrónica, circuitos, redes y programación. La credibilidad de la propuesta ante el decano depende de haber marcado esas asignaturas como no aplicables.
A39: • Con Biomédica, Multimedia y Electrónica plantear la conversación como coinversión en un desarrollo propio (DP-12, DP-11) y no como venta de licencias: el portafolio actual no les alcanza y ofrecerlo igual desgasta la relación.
A40: • Levantar los microcurrículos de las 15 asignaturas priorizadas antes de la reunión: las competencias de este análisis son inferencias basadas en el nombre y la ubicación de cada asignatura.
A41: • Verificar con la facultad las tres inconsistencias de créditos detectadas en las láminas (Sistemas S5, Multimedia S6, Electrónica S6) y el SNIES repetido entre Electrónica y Biológica: mencionarlo con tacto demuestra que el análisis se hizo asignatura por asignatura.

Sheet Catálogo CompanyGame
A1: Catálogo CompanyGame y su aplicación a la Facultad de Ingeniería
A2: 41 simuladores en 7 familias, según el cuadro de portafolio entregado por el cliente
A4: Familia | B4: Simulador | C4: Nivel | D4: Aplicación en los siete programas de esta facultad
A5: Negocios y estrategia | B5: T-Shirt | C5: Niveles 1 a 2 | D5: La familia con más recorrido. Gestión Estratégica Organizacional (Industrial), Desarrollo de Aplicaciones Empresariales (Sistemas) y las prácticas profesionales de los siete programas. T-Shirt y Sunny Day cubren Introducción a la Ingeniería, presente en los siete planes: la entrada de mayor volumen de estudiantes.
B6: Sunny Day | C6: Niveles 1 a 2
B7: Energy&Co | C7: Niveles 1 a 2
B8: Business21 | C8: Niveles 3 y 4
B9: Businessglobal | C9: Nivel 5
B10: Business Strategy | C10: Niveles 6 y 7
A11: Marketing y ventas | B11: MarketGame | C11: Niveles 1 a 2 | D11: Aplica en dos asignaturas: Investigación de Mercados (Industrial, 5) y Mercadeo e Investigación de Mercados (Agroindustrial, 4). Los cuatro niveles de la familia permiten ajustar la propuesta al presupuesto.
B12: Coffee Time | C12: Niveles 1 a 2
B13: SalesManager | C13: Niveles 3 y 4
B14: Food Company | C14: Niveles 3 y 4
B15: TechCompany | C15: Nivel 5
B16: GlobalMARKET | C16: Niveles 6 y 7
B17: FOCUS | C17: Niveles 6 y 7
A18: Finanzas y banca | B18: ContaTrainer | C18: Niveles 1 a 2 | D18: ContaTrainer y Kapital aplican en Ingeniería de Costos (Industrial y Biológica) e Ingeniería Económica (Industrial y Agroindustrial). Los simuladores de banca no tienen asignatura destino en esta facultad.
B19: Advisor Jr. | C19: Niveles 3 y 4
B20: CORBATUL | C20: Niveles 3 y 4
B21: Bankgame | C21: Nivel 5
B22: Kapital | C22: Nivel 5
B23: BANKCOMPANY | C23: Niveles 6 y 7
A24: Emprendimiento | B24: FitnessGym | C24: Niveles 3 y 4 | D24: Hallazgo principal del análisis: CÁTEDRA DE EMPRENDIMIENTO (Sistemas, semestre 7) es el único espacio de emprendimiento de los siete programas y el encaje más natural de todo el catálogo. También entra por Evaluación de Proyectos de Software y Valoración de Proyectos.
B25: Luxe Atelier | C25: Niveles 3 y 4
B26: Business Chef | C26: Nivel 5
B27: FitnessGym Executive | C27: Niveles 6 y 7
A28: Business Transformation | B28: InnovaTech | C28: Niveles 3 y 4 | D28: InnovaTech encaja de forma perfecta en Diseño de Productos y Servicios (Industrial), Gestión de Productos Tecnológicos (Electrónica) y Prototipado de Soluciones Tecnológicas. TRANSFORMA y Global2030 aplican en GestiónDigital de Sistemas Agropecuarios, Analítica de Datos y Seguridad Informática. Organization & People Management cubre la dimensión de equipos de la línea de software y de Ingeniería del Factor Humano.
B29: InterPyme | C29: Niveles 3 y 4
B30: Avocado Expand | C30: Niveles 3 y 4
B31: Acelera | C31: Niveles 3 y 4 / Nivel 5
B32: Organization & People Management | C32: Niveles 3 y 4 / Nivel 5
B33: Global2020 | C33: Nivel 5
B34: TRANSFORMA | C34: Niveles 6 y 7
B35: Global2030 | C35: Niveles 6 y 7
A36: HORECA | B36: Hotel Virtual | C36: Niveles 1 a 2 | D36: No aplica. Ninguna de las 412 asignaturas de los siete programas trabaja el sector hotelero o de restauración. Se marca como 'No encaja' de forma explícita: su destino en esta universidad serían programas de otras facultades, no Ingeniería.
B37: hotel game | C37: Niveles 1 a 2
B38: Casa Guadalupe | C38: Niveles 3 y 4
B39: Five Stars | C39: Niveles 3 y 4
B40: InnovaHotel | C40: Nivel 5
B41: Hotel Manager | C41: Niveles 6 y 7
B42: HotelCompany | C42: Niveles 6 y 7
A43: ESG Management | B43: ESGProject | C43: Niveles 3 y 4 | D43: Encaje transversal por el sello franciscano: Franciscanismo y Ecología (Sistemas y Biomédica), Ecología Agrícola y Agricultura Regenerativa (Biológica), Ética y Ética en Ingeniería Biológica, y de forma parcial Gestión de Calidad. Es la familia que mejor conecta con la identidad institucional de la universidad.
B44: ESGManagement | C44: Nivel 5
B45: GlobalManagement | C45: Niveles 6 y 7
